<?xml version="1.0" encoding="UTF-8"?>
<CobaltLog>
 <TE>
  <S>
   <P>
    <TC t="0" n="3" st0="2" sz0="31" st1="124" sz1="31" st2="7688" sz2="2" />
    <TA t="0" n="3" st0="2" sz0="32" st1="128" sz1="31" st2="7936" sz2="2" />
    <TB t="0" n="3" st0="2" sz0="31" st1="124" sz1="32" st2="7936" sz2="2" />
    <O t="0" a="0" b="0" o="1" nF="2" nB="1" nS="1" >
     <IA n="3" i0="3" i1="0" i2="2" />
     <IB n="3" i0="1" i1="3" i2="2" />
    </O>
    <DP n="1" d0="Hawaii" CU0="44" MHz0="720" FPC0="128" />
   </P>
   <ID kG0="1" kG1="1" kG2="1" b0="2" b1="2" ppdO="0" ppdLS="0" ppdAll="0" >
    <K i="0" wG0="8" wG1="8" mT0="2" mT1="2" b0="2" b1="2" nlpaA="1" lspaA="16" tspaA="16" nlpeA="4" lspeA="4" tspeA="16" nlpaB="4" lspaB="4" tspaB="16" nlpeB="1" lspeB="16" tspeB="16" u0="16" u1="0" />
   </ID>
  </S>
  <B t="0.136400" u="ms" />
 </TE>
 <TE>
  <S>
   <P>
    <TC t="0" n="3" st0="2" sz0="111" st1="444" sz1="111" st2="98568" sz2="2" />
    <TA t="0" n="3" st0="2" sz0="111" st1="444" sz1="111" st2="98568" sz2="2" />
    <TB t="0" n="3" st0="2" sz0="111" st1="444" sz1="111" st2="98568" sz2="2" />
    <O t="0" a="0" b="0" o="1" nF="2" nB="1" nS="1" >
     <IA n="3" i0="3" i1="0" i2="2" />
     <IB n="3" i0="1" i1="3" i2="2" />
    </O>
    <DP n="1" d0="Hawaii" CU0="44" MHz0="720" FPC0="128" />
   </P>
   <ID kG0="1" kG1="1" kG2="1" b0="2" b1="2" ppdO="0" ppdLS="0" ppdAll="0" >
    <K i="0" wG0="8" wG1="8" mT0="2" mT1="2" b0="2" b1="2" nlpaA="1" lspaA="4" tspaA="4" nlpeA="1" lspeA="16" tspeA="16" nlpaB="1" lspaB="16" tspaB="16" nlpeB="1" lspeB="4" tspeB="4" u0="4" u1="1" />
   </ID>
  </S>
  <B t="0.165733" u="ms" />
 </TE>
 <TE>
  <S>
   <P>
    <TC t="0" n="3" st0="2" sz0="31" st1="124" sz1="31" st2="7688" sz2="2" />
    <TA t="0" n="3" st0="2" sz0="32" st1="128" sz1="31" st2="7936" sz2="2" />
    <TB t="0" n="3" st0="2" sz0="31" st1="124" sz1="32" st2="7936" sz2="2" />
    <O t="0" a="0" b="0" o="1" nF="2" nB="1" nS="1" >
     <IA n="3" i0="3" i1="0" i2="2" />
     <IB n="3" i0="1" i1="3" i2="2" />
    </O>
    <DP n="1" d0="Hawaii" CU0="44" MHz0="720" FPC0="128" />
   </P>
   <ID kG0="1" kG1="1" kG2="1" b0="2" b1="2" ppdO="0" ppdLS="0" ppdAll="0" >
    <K i="0" wG0="8" wG1="8" mT0="3" mT1="3" b0="2" b1="2" nlpaA="1" lspaA="4" tspaA="4" nlpeA="2" lspeA="16" tspeA="24" nlpaB="1" lspaB="24" tspaB="24" nlpeB="2" lspeB="2" tspeB="4" u0="4" u1="0" />
   </ID>
  </S>
  <B t="0.142756" u="ms" />
 </TE>
 <TE>
  <S>
   <P>
    <TC t="0" n="3" st0="2" sz0="1935" st1="7740" sz1="1935" st2="29953800" sz2="2" />
    <TA t="0" n="3" st0="2" sz0="1935" st1="7740" sz1="1935" st2="29953800" sz2="2" />
    <TB t="0" n="3" st0="2" sz0="1935" st1="7740" sz1="1935" st2="29953800" sz2="2" />
    <O t="0" a="0" b="0" o="1" nF="2" nB="1" nS="1" >
     <IA n="3" i0="3" i1="0" i2="2" />
     <IB n="3" i0="1" i1="3" i2="2" />
    </O>
    <DP n="1" d0="Hawaii" CU0="44" MHz0="720" FPC0="128" />
   </P>
   <ID kG0="2" kG1="2" kG2="1" b0="1" b1="1" ppdO="0" ppdLS="0" ppdAll="0" >
    <K i="0" wG0="16" wG1="16" mT0="4" mT1="4" b0="0" b1="0" nlpaA="1" lspaA="16" tspaA="16" nlpeA="4" lspeA="16" tspeA="64" nlpaB="4" lspaB="16" tspaB="64" nlpeB="1" lspeB="16" tspeB="16" u0="16" u1="1" />
    <K i="1" wG0="16" wG1="16" mT0="4" mT1="4" b0="1" b1="0" nlpaA="1" lspaA="16" tspaA="16" nlpeA="4" lspeA="16" tspeA="64" nlpaB="4" lspaB="16" tspaB="64" nlpeB="1" lspeB="16" tspeB="16" u0="16" u1="1" />
    <K i="2" wG0="16" wG1="16" mT0="4" mT1="4" b0="0" b1="1" nlpaA="1" lspaA="16" tspaA="16" nlpeA="4" lspeA="16" tspeA="64" nlpaB="4" lspaB="16" tspaB="64" nlpeB="1" lspeB="16" tspeB="16" u0="16" u1="1" />
    <K i="3" wG0="16" wG1="16" mT0="4" mT1="4" b0="1" b1="1" nlpaA="1" lspaA="16" tspaA="16" nlpeA="4" lspeA="16" tspeA="64" nlpaB="4" lspaB="16" tspaB="64" nlpeB="1" lspeB="16" tspeB="16" u0="16" u1="1" />
   </ID>
  </S>
  <B t="11.811557" u="ms" />
 </TE>
 <TE>
  <S>
   <P>
    <TC t="0" n="3" st0="2" sz0="352" st1="1408" sz1="352" st2="991232" sz2="2" />
    <TA t="0" n="3" st0="2" sz0="352" st1="1408" sz1="352" st2="991232" sz2="2" />
    <TB t="0" n="3" st0="2" sz0="352" st1="1408" sz1="352" st2="991232" sz2="2" />
    <O t="0" a="0" b="0" o="1" nF="2" nB="1" nS="1" >
     <IA n="3" i0="3" i1="0" i2="2" />
     <IB n="3" i0="1" i1="3" i2="2" />
    </O>
    <DP n="1" d0="Hawaii" CU0="44" MHz0="720" FPC0="128" />
   </P>
   <ID kG0="2" kG1="2" kG2="1" b0="1" b1="1" ppdO="0" ppdLS="0" ppdAll="0" >
    <K i="0" wG0="16" wG1="16" mT0="2" mT1="2" b0="0" b1="0" nlpaA="1" lspaA="8" tspaA="8" nlpeA="1" lspeA="32" tspeA="32" nlpaB="1" lspaB="32" tspaB="32" nlpeB="1" lspeB="8" tspeB="8" u0="8" u1="0" />
    <K i="1" wG0="16" wG1="16" mT0="2" mT1="2" b0="1" b1="0" nlpaA="1" lspaA="8" tspaA="8" nlpeA="1" lspeA="32" tspeA="32" nlpaB="1" lspaB="32" tspaB="32" nlpeB="1" lspeB="8" tspeB="8" u0="8" u1="0" />
    <K i="2" wG0="16" wG1="16" mT0="2" mT1="2" b0="0" b1="1" nlpaA="1" lspaA="8" tspaA="8" nlpeA="1" lspeA="32" tspeA="32" nlpaB="1" lspaB="32" tspaB="32" nlpeB="1" lspeB="8" tspeB="8" u0="8" u1="0" />
    <K i="3" wG0="16" wG1="16" mT0="2" mT1="2" b0="1" b1="1" nlpaA="1" lspaA="8" tspaA="8" nlpeA="1" lspeA="32" tspeA="32" nlpaB="1" lspaB="32" tspaB="32" nlpeB="1" lspeB="8" tspeB="8" u0="8" u1="0" />
   </ID>
  </S>
  <B t="0.242978" u="ms" />
 </TE>
 <TE>
  <S>
   <P>
    <TC t="0" n="3" st0="2" sz0="463" st1="1852" sz1="463" st2="1714952" sz2="2" />
    <TA t="0" n="3" st0="2" sz0="464" st1="1856" sz1="463" st2="1718656" sz2="2" />
    <TB t="0" n="3" st0="2" sz0="463" st1="1852" sz1="464" st2="1718656" sz2="2" />
    <O t="0" a="0" b="0" o="1" nF="2" nB="1" nS="1" >
     <IA n="3" i0="3" i1="0" i2="2" />
     <IB n="3" i0="1" i1="3" i2="2" />
    </O>
    <DP n="1" d0="Hawaii" CU0="44" MHz0="720" FPC0="128" />
   </P>
   <ID kG0="1" kG1="1" kG2="1" b0="2" b1="2" ppdO="0" ppdLS="0" ppdAll="0" >
    <K i="0" wG0="16" wG1="16" mT0="4" mT1="4" b0="2" b1="2" nlpaA="1" lspaA="16" tspaA="16" nlpeA="4" lspeA="16" tspeA="64" nlpaB="4" lspaB="16" tspaB="64" nlpeB="1" lspeB="16" tspeB="16" u0="16" u1="0" />
   </ID>
  </S>
  <B t="0.373022" u="ms" />
 </TE>
 <TE>
  <S>
   <P>
    <TC t="0" n="3" st0="2" sz0="2464" st1="9856" sz1="2464" st2="48570368" sz2="2" />
    <TA t="0" n="3" st0="2" sz0="2463" st1="9852" sz1="2464" st2="48550656" sz2="2" />
    <TB t="0" n="3" st0="2" sz0="2464" st1="9856" sz1="2463" st2="48550656" sz2="2" />
    <O t="0" a="0" b="0" o="1" nF="2" nB="1" nS="1" >
     <IA n="3" i0="3" i1="0" i2="2" />
     <IB n="3" i0="1" i1="3" i2="2" />
    </O>
    <DP n="1" d0="Hawaii" CU0="44" MHz0="720" FPC0="128" />
   </P>
   <ID kG0="2" kG1="2" kG2="1" b0="1" b1="1" ppdO="0" ppdLS="0" ppdAll="0" >
    <K i="0" wG0="16" wG1="16" mT0="4" mT1="4" b0="0" b1="0" nlpaA="1" lspaA="16" tspaA="16" nlpeA="4" lspeA="16" tspeA="64" nlpaB="4" lspaB="16" tspaB="64" nlpeB="1" lspeB="16" tspeB="16" u0="16" u1="1" />
    <K i="1" wG0="16" wG1="16" mT0="4" mT1="4" b0="1" b1="0" nlpaA="1" lspaA="16" tspaA="16" nlpeA="4" lspeA="16" tspeA="64" nlpaB="4" lspaB="16" tspaB="64" nlpeB="1" lspeB="16" tspeB="16" u0="16" u1="1" />
    <K i="2" wG0="16" wG1="16" mT0="4" mT1="4" b0="0" b1="1" nlpaA="1" lspaA="16" tspaA="16" nlpeA="4" lspeA="16" tspeA="64" nlpaB="4" lspaB="16" tspaB="64" nlpeB="1" lspeB="16" tspeB="16" u0="16" u1="1" />
    <K i="3" wG0="16" wG1="16" mT0="4" mT1="4" b0="1" b1="1" nlpaA="1" lspaA="16" tspaA="16" nlpeA="4" lspeA="16" tspeA="64" nlpaB="4" lspaB="16" tspaB="64" nlpeB="1" lspeB="16" tspeB="16" u0="16" u1="1" />
   </ID>
  </S>
  <B t="24.065559" u="ms" />
 </TE>
 <TE>
  <S>
   <P>
    <TC t="0" n="3" st0="2" sz0="256" st1="1024" sz1="256" st2="524288" sz2="2" />
    <TA t="0" n="3" st0="2" sz0="255" st1="1020" sz1="256" st2="522240" sz2="2" />
    <TB t="0" n="3" st0="2" sz0="256" st1="1024" sz1="255" st2="522240" sz2="2" />
    <O t="0" a="0" b="0" o="1" nF="2" nB="1" nS="1" >
     <IA n="3" i0="3" i1="0" i2="2" />
     <IB n="3" i0="1" i1="3" i2="2" />
    </O>
    <DP n="1" d0="Hawaii" CU0="44" MHz0="720" FPC0="128" />
   </P>
   <ID kG0="1" kG1="1" kG2="1" b0="2" b1="2" ppdO="0" ppdLS="0" ppdAll="0" >
    <K i="0" wG0="16" wG1="16" mT0="3" mT1="3" b0="2" b1="2" nlpaA="1" lspaA="16" tspaA="16" nlpeA="3" lspeA="16" tspeA="48" nlpaB="3" lspaB="16" tspaB="48" nlpeB="1" lspeB="16" tspeB="16" u0="16" u1="1" />
   </ID>
  </S>
  <B t="0.286489" u="ms" />
 </TE>
 <TE>
  <S>
   <P>
    <TC t="0" n="3" st0="2" sz0="112" st1="448" sz1="112" st2="100352" sz2="2" />
    <TA t="0" n="3" st0="2" sz0="111" st1="444" sz1="112" st2="99456" sz2="2" />
    <TB t="0" n="3" st0="2" sz0="112" st1="448" sz1="111" st2="99456" sz2="2" />
    <O t="0" a="0" b="0" o="1" nF="2" nB="1" nS="1" >
     <IA n="3" i0="3" i1="0" i2="2" />
     <IB n="3" i0="1" i1="3" i2="2" />
    </O>
    <DP n="1" d0="Hawaii" CU0="44" MHz0="720" FPC0="128" />
   </P>
   <ID kG0="1" kG1="1" kG2="1" b0="2" b1="2" ppdO="0" ppdLS="0" ppdAll="0" >
    <K i="0" wG0="16" wG1="16" mT0="2" mT1="2" b0="2" b1="2" nlpaA="1" lspaA="8" tspaA="8" nlpeA="1" lspeA="32" tspeA="32" nlpaB="1" lspaB="32" tspaB="32" nlpeB="1" lspeB="8" tspeB="8" u0="8" u1="1" />
   </ID>
  </S>
  <B t="0.160356" u="ms" />
 </TE>
 <TE>
  <S>
   <P>
    <TC t="0" n="3" st0="2" sz0="1472" st1="5888" sz1="1472" st2="17334272" sz2="2" />
    <TA t="0" n="3" st0="2" sz0="1471" st1="5884" sz1="1472" st2="17322496" sz2="2" />
    <TB t="0" n="3" st0="2" sz0="1472" st1="5888" sz1="1471" st2="17322496" sz2="2" />
    <O t="0" a="0" b="0" o="1" nF="2" nB="1" nS="1" >
     <IA n="3" i0="3" i1="0" i2="2" />
     <IB n="3" i0="1" i1="3" i2="2" />
    </O>
    <DP n="1" d0="Hawaii" CU0="44" MHz0="720" FPC0="128" />
   </P>
   <ID kG0="1" kG1="1" kG2="1" b0="2" b1="2" ppdO="0" ppdLS="0" ppdAll="0" >
    <K i="0" wG0="16" wG1="16" mT0="5" mT1="5" b0="2" b1="2" nlpaA="1" lspaA="16" tspaA="16" nlpeA="5" lspeA="16" tspeA="80" nlpaB="5" lspaB="16" tspaB="80" nlpeB="1" lspeB="16" tspeB="16" u0="16" u1="1" />
   </ID>
  </S>
  <B t="6.333556" u="ms" />
 </TE>
 <TE>
  <S>
   <P>
    <TC t="0" n="3" st0="2" sz0="591" st1="2364" sz1="591" st2="2794248" sz2="2" />
    <TA t="0" n="3" st0="2" sz0="591" st1="2364" sz1="591" st2="2794248" sz2="2" />
    <TB t="0" n="3" st0="2" sz0="591" st1="2364" sz1="591" st2="2794248" sz2="2" />
    <O t="0" a="0" b="0" o="1" nF="2" nB="1" nS="1" >
     <IA n="3" i0="3" i1="0" i2="2" />
     <IB n="3" i0="1" i1="3" i2="2" />
    </O>
    <DP n="1" d0="Hawaii" CU0="44" MHz0="720" FPC0="128" />
   </P>
   <ID kG0="1" kG1="1" kG2="1" b0="2" b1="2" ppdO="0" ppdLS="0" ppdAll="0" >
    <K i="0" wG0="16" wG1="16" mT0="5" mT1="5" b0="2" b1="2" nlpaA="1" lspaA="16" tspaA="16" nlpeA="5" lspeA="16" tspeA="80" nlpaB="5" lspaB="16" tspaB="80" nlpeB="1" lspeB="16" tspeB="16" u0="16" u1="1" />
   </ID>
  </S>
  <B t="0.581778" u="ms" />
 </TE>
 <TE>
  <S>
   <P>
    <TC t="0" n="3" st0="2" sz0="1695" st1="6780" sz1="1695" st2="22984200" sz2="2" />
    <TA t="0" n="3" st0="2" sz0="1695" st1="6780" sz1="1695" st2="22984200" sz2="2" />
    <TB t="0" n="3" st0="2" sz0="1695" st1="6780" sz1="1695" st2="22984200" sz2="2" />
    <O t="0" a="0" b="0" o="1" nF="2" nB="1" nS="1" >
     <IA n="3" i0="3" i1="0" i2="2" />
     <IB n="3" i0="1" i1="3" i2="2" />
    </O>
    <DP n="1" d0="Hawaii" CU0="44" MHz0="720" FPC0="128" />
   </P>
   <ID kG0="2" kG1="2" kG2="1" b0="1" b1="1" ppdO="0" ppdLS="0" ppdAll="0" >
    <K i="0" wG0="16" wG1="16" mT0="4" mT1="4" b0="0" b1="0" nlpaA="1" lspaA="16" tspaA="16" nlpeA="4" lspeA="16" tspeA="64" nlpaB="4" lspaB="16" tspaB="64" nlpeB="1" lspeB="16" tspeB="16" u0="16" u1="1" />
    <K i="1" wG0="16" wG1="16" mT0="4" mT1="4" b0="1" b1="0" nlpaA="1" lspaA="16" tspaA="16" nlpeA="4" lspeA="16" tspeA="64" nlpaB="4" lspaB="16" tspaB="64" nlpeB="1" lspeB="16" tspeB="16" u0="16" u1="1" />
    <K i="2" wG0="16" wG1="16" mT0="4" mT1="4" b0="0" b1="1" nlpaA="1" lspaA="16" tspaA="16" nlpeA="4" lspeA="16" tspeA="64" nlpaB="4" lspaB="16" tspaB="64" nlpeB="1" lspeB="16" tspeB="16" u0="16" u1="1" />
    <K i="3" wG0="16" wG1="16" mT0="4" mT1="4" b0="1" b1="1" nlpaA="1" lspaA="16" tspaA="16" nlpeA="4" lspeA="16" tspeA="64" nlpaB="4" lspaB="16" tspaB="64" nlpeB="1" lspeB="16" tspeB="16" u0="16" u1="1" />
   </ID>
  </S>
  <B t="9.680979" u="ms" />
 </TE>
 <TE>
  <S>
   <P>
    <TC t="0" n="3" st0="2" sz0="175" st1="700" sz1="175" st2="245000" sz2="2" />
    <TA t="0" n="3" st0="2" sz0="175" st1="700" sz1="175" st2="245000" sz2="2" />
    <TB t="0" n="3" st0="2" sz0="175" st1="700" sz1="175" st2="245000" sz2="2" />
    <O t="0" a="0" b="0" o="1" nF="2" nB="1" nS="1" >
     <IA n="3" i0="3" i1="0" i2="2" />
     <IB n="3" i0="1" i1="3" i2="2" />
    </O>
    <DP n="1" d0="Hawaii" CU0="44" MHz0="720" FPC0="128" />
   </P>
   <ID kG0="1" kG1="1" kG2="1" b0="2" b1="2" ppdO="0" ppdLS="0" ppdAll="0" >
    <K i="0" wG0="8" wG1="8" mT0="2" mT1="2" b0="2" b1="2" nlpaA="1" lspaA="4" tspaA="4" nlpeA="1" lspeA="16" tspeA="16" nlpaB="1" lspaB="16" tspaB="16" nlpeB="1" lspeB="4" tspeB="4" u0="4" u1="1" />
   </ID>
  </S>
  <B t="0.194089" u="ms" />
 </TE>
 <TE>
  <S>
   <P>
    <TC t="0" n="3" st0="2" sz0="1264" st1="5056" sz1="1264" st2="12781568" sz2="2" />
    <TA t="0" n="3" st0="2" sz0="1263" st1="5052" sz1="1264" st2="12771456" sz2="2" />
    <TB t="0" n="3" st0="2" sz0="1264" st1="5056" sz1="1263" st2="12771456" sz2="2" />
    <O t="0" a="0" b="0" o="1" nF="2" nB="1" nS="1" >
     <IA n="3" i0="3" i1="0" i2="2" />
     <IB n="3" i0="1" i1="3" i2="2" />
    </O>
    <DP n="1" d0="Hawaii" CU0="44" MHz0="720" FPC0="128" />
   </P>
   <ID kG0="1" kG1="1" kG2="1" b0="2" b1="2" ppdO="0" ppdLS="0" ppdAll="0" >
    <K i="0" wG0="16" wG1="16" mT0="4" mT1="4" b0="2" b1="2" nlpaA="1" lspaA="4" tspaA="4" nlpeA="1" lspeA="64" tspeA="64" nlpaB="1" lspaB="64" tspaB="64" nlpeB="1" lspeB="4" tspeB="4" u0="4" u1="1" />
   </ID>
  </S>
  <B t="3.945823" u="ms" />
 </TE>
 <TE>
  <S>
   <P>
    <TC t="0" n="3" st0="2" sz0="2192" st1="8768" sz1="2192" st2="38438912" sz2="2" />
    <TA t="0" n="3" st0="2" sz0="2192" st1="8768" sz1="2192" st2="38438912" sz2="2" />
    <TB t="0" n="3" st0="2" sz0="2192" st1="8768" sz1="2192" st2="38438912" sz2="2" />
    <O t="0" a="0" b="0" o="1" nF="2" nB="1" nS="1" >
     <IA n="3" i0="3" i1="0" i2="2" />
     <IB n="3" i0="1" i1="3" i2="2" />
    </O>
    <DP n="1" d0="Hawaii" CU0="44" MHz0="720" FPC0="128" />
   </P>
   <ID kG0="1" kG1="1" kG2="1" b0="2" b1="2" ppdO="0" ppdLS="0" ppdAll="0" >
    <K i="0" wG0="16" wG1="16" mT0="5" mT1="5" b0="2" b1="2" nlpaA="1" lspaA="16" tspaA="16" nlpeA="5" lspeA="16" tspeA="80" nlpaB="5" lspaB="16" tspaB="80" nlpeB="1" lspeB="16" tspeB="16" u0="16" u1="0" />
   </ID>
  </S>
  <B t="15.537380" u="ms" />
 </TE>
 <TE>
  <S>
   <P>
    <TC t="0" n="3" st0="2" sz0="352" st1="1408" sz1="352" st2="991232" sz2="2" />
    <TA t="0" n="3" st0="2" sz0="351" st1="1404" sz1="352" st2="988416" sz2="2" />
    <TB t="0" n="3" st0="2" sz0="352" st1="1408" sz1="351" st2="988416" sz2="2" />
    <O t="0" a="0" b="0" o="1" nF="2" nB="1" nS="1" >
     <IA n="3" i0="3" i1="0" i2="2" />
     <IB n="3" i0="1" i1="3" i2="2" />
    </O>
    <DP n="1" d0="Hawaii" CU0="44" MHz0="720" FPC0="128" />
   </P>
   <ID kG0="1" kG1="1" kG2="1" b0="2" b1="2" ppdO="0" ppdLS="0" ppdAll="0" >
    <K i="0" wG0="16" wG1="16" mT0="3" mT1="3" b0="2" b1="2" nlpaA="1" lspaA="16" tspaA="16" nlpeA="3" lspeA="16" tspeA="48" nlpaB="3" lspaB="16" tspaB="48" nlpeB="1" lspeB="16" tspeB="16" u0="16" u1="1" />
   </ID>
  </S>
  <B t="0.249822" u="ms" />
 </TE>
 <TE>
  <S>
   <P>
    <TC t="0" n="3" st0="2" sz0="2192" st1="8768" sz1="2192" st2="38438912" sz2="2" />
    <TA t="0" n="3" st0="2" sz0="2192" st1="8768" sz1="2192" st2="38438912" sz2="2" />
    <TB t="0" n="3" st0="2" sz0="2192" st1="8768" sz1="2192" st2="38438912" sz2="2" />
    <O t="0" a="0" b="0" o="1" nF="2" nB="1" nS="1" >
     <IA n="3" i0="3" i1="0" i2="2" />
     <IB n="3" i0="1" i1="3" i2="2" />
    </O>
    <DP n="1" d0="Hawaii" CU0="44" MHz0="720" FPC0="128" />
   </P>
   <ID kG0="1" kG1="1" kG2="1" b0="2" b1="2" ppdO="0" ppdLS="0" ppdAll="0" >
    <K i="0" wG0="16" wG1="16" mT0="6" mT1="6" b0="2" b1="2" nlpaA="1" lspaA="16" tspaA="16" nlpeA="6" lspeA="16" tspeA="96" nlpaB="6" lspaB="16" tspaB="96" nlpeB="1" lspeB="16" tspeB="16" u0="16" u1="0" />
   </ID>
  </S>
  <B t="15.857113" u="ms" />
 </TE>
 <TE>
  <S>
   <P>
    <TC t="0" n="3" st0="2" sz0="2464" st1="9856" sz1="2464" st2="48570368" sz2="2" />
    <TA t="0" n="3" st0="2" sz0="2464" st1="9856" sz1="2464" st2="48570368" sz2="2" />
    <TB t="0" n="3" st0="2" sz0="2464" st1="9856" sz1="2464" st2="48570368" sz2="2" />
    <O t="0" a="0" b="0" o="1" nF="2" nB="1" nS="1" >
     <IA n="3" i0="3" i1="0" i2="2" />
     <IB n="3" i0="1" i1="3" i2="2" />
    </O>
    <DP n="1" d0="Hawaii" CU0="44" MHz0="720" FPC0="128" />
   </P>
   <ID kG0="1" kG1="1" kG2="1" b0="2" b1="2" ppdO="0" ppdLS="0" ppdAll="0" >
    <K i="0" wG0="16" wG1="16" mT0="6" mT1="6" b0="2" b1="2" nlpaA="1" lspaA="16" tspaA="16" nlpeA="6" lspeA="16" tspeA="96" nlpaB="6" lspaB="16" tspaB="96" nlpeB="1" lspeB="16" tspeB="16" u0="16" u1="0" />
   </ID>
  </S>
  <B t="22.312892" u="ms" />
 </TE>
 <TE>
  <S>
   <P>
    <TC t="0" n="3" st0="2" sz0="896" st1="3584" sz1="896" st2="6422528" sz2="2" />
    <TA t="0" n="3" st0="2" sz0="895" st1="3580" sz1="896" st2="6415360" sz2="2" />
    <TB t="0" n="3" st0="2" sz0="896" st1="3584" sz1="895" st2="6415360" sz2="2" />
    <O t="0" a="0" b="0" o="1" nF="2" nB="1" nS="1" >
     <IA n="3" i0="3" i1="0" i2="2" />
     <IB n="3" i0="1" i1="3" i2="2" />
    </O>
    <DP n="1" d0="Hawaii" CU0="44" MHz0="720" FPC0="128" />
   </P>
   <ID kG0="2" kG1="2" kG2="1" b0="1" b1="1" ppdO="0" ppdLS="0" ppdAll="0" >
    <K i="0" wG0="16" wG1="16" mT0="7" mT1="7" b0="0" b1="0" nlpaA="1" lspaA="16" tspaA="16" nlpeA="7" lspeA="16" tspeA="112" nlpaB="7" lspaB="16" tspaB="112" nlpeB="1" lspeB="16" tspeB="16" u0="16" u1="1" />
    <K i="1" wG0="16" wG1="16" mT0="7" mT1="7" b0="1" b1="0" nlpaA="1" lspaA="16" tspaA="16" nlpeA="7" lspeA="16" tspeA="112" nlpaB="7" lspaB="16" tspaB="112" nlpeB="1" lspeB="16" tspeB="16" u0="16" u1="1" />
    <K i="2" wG0="16" wG1="16" mT0="7" mT1="7" b0="0" b1="1" nlpaA="1" lspaA="16" tspaA="16" nlpeA="7" lspeA="16" tspeA="112" nlpaB="7" lspaB="16" tspaB="112" nlpeB="1" lspeB="16" tspeB="16" u0="16" u1="1" />
    <K i="3" wG0="16" wG1="16" mT0="7" mT1="7" b0="1" b1="1" nlpaA="1" lspaA="16" tspaA="16" nlpeA="7" lspeA="16" tspeA="112" nlpaB="7" lspaB="16" tspaB="112" nlpeB="1" lspeB="16" tspeB="16" u0="16" u1="1" />
   </ID>
  </S>
  <B t="1.435378" u="ms" />
 </TE>
 <TE>
  <S>
   <P>
    <TC t="0" n="3" st0="2" sz0="1263" st1="5052" sz1="1263" st2="12761352" sz2="2" />
    <TA t="0" n="3" st0="2" sz0="1263" st1="5052" sz1="1263" st2="12761352" sz2="2" />
    <TB t="0" n="3" st0="2" sz0="1263" st1="5052" sz1="1263" st2="12761352" sz2="2" />
    <O t="0" a="0" b="0" o="1" nF="2" nB="1" nS="1" >
     <IA n="3" i0="3" i1="0" i2="2" />
     <IB n="3" i0="1" i1="3" i2="2" />
    </O>
    <DP n="1" d0="Hawaii" CU0="44" MHz0="720" FPC0="128" />
   </P>
   <ID kG0="1" kG1="1" kG2="1" b0="2" b1="2" ppdO="0" ppdLS="0" ppdAll="0" >
    <K i="0" wG0="16" wG1="16" mT0="4" mT1="4" b0="2" b1="2" nlpaA="1" lspaA="4" tspaA="4" nlpeA="1" lspeA="64" tspeA="64" nlpaB="1" lspaB="64" tspaB="64" nlpeB="1" lspeB="4" tspeB="4" u0="4" u1="1" />
   </ID>
  </S>
  <B t="4.225956" u="ms" />
 </TE>
 <TE>
  <S>
   <P>
    <TC t="0" n="3" st0="2" sz0="1471" st1="5884" sz1="1471" st2="17310728" sz2="2" />
    <TA t="0" n="3" st0="2" sz0="1471" st1="5884" sz1="1471" st2="17310728" sz2="2" />
    <TB t="0" n="3" st0="2" sz0="1471" st1="5884" sz1="1471" st2="17310728" sz2="2" />
    <O t="0" a="0" b="0" o="1" nF="2" nB="1" nS="1" >
     <IA n="3" i0="3" i1="0" i2="2" />
     <IB n="3" i0="1" i1="3" i2="2" />
    </O>
    <DP n="1" d0="Hawaii" CU0="44" MHz0="720" FPC0="128" />
   </P>
   <ID kG0="2" kG1="2" kG2="1" b0="1" b1="1" ppdO="0" ppdLS="0" ppdAll="0" >
    <K i="0" wG0="16" wG1="16" mT0="4" mT1="4" b0="0" b1="0" nlpaA="1" lspaA="16" tspaA="16" nlpeA="4" lspeA="16" tspeA="64" nlpaB="4" lspaB="16" tspaB="64" nlpeB="1" lspeB="16" tspeB="16" u0="16" u1="1" />
    <K i="1" wG0="16" wG1="16" mT0="4" mT1="4" b0="1" b1="0" nlpaA="1" lspaA="16" tspaA="16" nlpeA="4" lspeA="16" tspeA="64" nlpaB="4" lspaB="16" tspaB="64" nlpeB="1" lspeB="16" tspeB="16" u0="16" u1="1" />
    <K i="2" wG0="16" wG1="16" mT0="4" mT1="4" b0="0" b1="1" nlpaA="1" lspaA="16" tspaA="16" nlpeA="4" lspeA="16" tspeA="64" nlpaB="4" lspaB="16" tspaB="64" nlpeB="1" lspeB="16" tspeB="16" u0="16" u1="1" />
    <K i="3" wG0="16" wG1="16" mT0="4" mT1="4" b0="1" b1="1" nlpaA="1" lspaA="16" tspaA="16" nlpeA="4" lspeA="16" tspeA="64" nlpaB="4" lspaB="16" tspaB="64" nlpeB="1" lspeB="16" tspeB="16" u0="16" u1="1" />
   </ID>
  </S>
  <B t="7.593912" u="ms" />
 </TE>
 <TE>
  <S>
   <P>
    <TC t="0" n="3" st0="2" sz0="2752" st1="11008" sz1="2752" st2="60588032" sz2="2" />
    <TA t="0" n="3" st0="2" sz0="2751" st1="11004" sz1="2752" st2="60566016" sz2="2" />
    <TB t="0" n="3" st0="2" sz0="2752" st1="11008" sz1="2751" st2="60566016" sz2="2" />
    <O t="0" a="0" b="0" o="1" nF="2" nB="1" nS="1" >
     <IA n="3" i0="3" i1="0" i2="2" />
     <IB n="3" i0="1" i1="3" i2="2" />
    </O>
    <DP n="1" d0="Hawaii" CU0="44" MHz0="720" FPC0="128" />
   </P>
   <ID kG0="2" kG1="2" kG2="1" b0="1" b1="1" ppdO="0" ppdLS="0" ppdAll="0" >
    <K i="0" wG0="16" wG1="16" mT0="5" mT1="5" b0="0" b1="0" nlpaA="1" lspaA="16" tspaA="16" nlpeA="5" lspeA="16" tspeA="80" nlpaB="5" lspaB="16" tspaB="80" nlpeB="1" lspeB="16" tspeB="16" u0="16" u1="1" />
    <K i="1" wG0="16" wG1="16" mT0="5" mT1="5" b0="1" b1="0" nlpaA="1" lspaA="16" tspaA="16" nlpeA="5" lspeA="16" tspeA="80" nlpaB="5" lspaB="16" tspaB="80" nlpeB="1" lspeB="16" tspeB="16" u0="16" u1="1" />
    <K i="2" wG0="16" wG1="16" mT0="5" mT1="5" b0="0" b1="1" nlpaA="1" lspaA="16" tspaA="16" nlpeA="5" lspeA="16" tspeA="80" nlpaB="5" lspaB="16" tspaB="80" nlpeB="1" lspeB="16" tspeB="16" u0="16" u1="1" />
    <K i="3" wG0="16" wG1="16" mT0="5" mT1="5" b0="1" b1="1" nlpaA="1" lspaA="16" tspaA="16" nlpeA="5" lspeA="16" tspeA="80" nlpaB="5" lspaB="16" tspaB="80" nlpeB="1" lspeB="16" tspeB="16" u0="16" u1="1" />
   </ID>
  </S>
  <B t="31.441915" u="ms" />
 </TE>
 <TE>
  <S>
   <P>
    <TC t="0" n="3" st0="2" sz0="896" st1="3584" sz1="896" st2="6422528" sz2="2" />
    <TA t="0" n="3" st0="2" sz0="896" st1="3584" sz1="896" st2="6422528" sz2="2" />
    <TB t="0" n="3" st0="2" sz0="896" st1="3584" sz1="896" st2="6422528" sz2="2" />
    <O t="0" a="0" b="0" o="1" nF="2" nB="1" nS="1" >
     <IA n="3" i0="3" i1="0" i2="2" />
     <IB n="3" i0="1" i1="3" i2="2" />
    </O>
    <DP n="1" d0="Hawaii" CU0="44" MHz0="720" FPC0="128" />
   </P>
   <ID kG0="2" kG1="2" kG2="1" b0="1" b1="1" ppdO="0" ppdLS="0" ppdAll="0" >
    <K i="0" wG0="16" wG1="16" mT0="4" mT1="4" b0="0" b1="0" nlpaA="1" lspaA="16" tspaA="16" nlpeA="4" lspeA="16" tspeA="64" nlpaB="4" lspaB="16" tspaB="64" nlpeB="1" lspeB="16" tspeB="16" u0="16" u1="0" />
    <K i="1" wG0="16" wG1="16" mT0="4" mT1="4" b0="1" b1="0" nlpaA="1" lspaA="16" tspaA="16" nlpeA="4" lspeA="16" tspeA="64" nlpaB="4" lspaB="16" tspaB="64" nlpeB="1" lspeB="16" tspeB="16" u0="16" u1="0" />
    <K i="2" wG0="16" wG1="16" mT0="4" mT1="4" b0="0" b1="1" nlpaA="1" lspaA="16" tspaA="16" nlpeA="4" lspeA="16" tspeA="64" nlpaB="4" lspaB="16" tspaB="64" nlpeB="1" lspeB="16" tspeB="16" u0="16" u1="0" />
    <K i="3" wG0="16" wG1="16" mT0="4" mT1="4" b0="1" b1="1" nlpaA="1" lspaA="16" tspaA="16" nlpeA="4" lspeA="16" tspeA="64" nlpaB="4" lspaB="16" tspaB="64" nlpeB="1" lspeB="16" tspeB="16" u0="16" u1="0" />
   </ID>
  </S>
  <B t="1.650978" u="ms" />
 </TE>
 <TE>
  <S>
   <P>
    <TC t="0" n="3" st0="2" sz0="1695" st1="6780" sz1="1695" st2="22984200" sz2="2" />
    <TA t="0" n="3" st0="2" sz0="1695" st1="6780" sz1="1695" st2="22984200" sz2="2" />
    <TB t="0" n="3" st0="2" sz0="1695" st1="6780" sz1="1695" st2="22984200" sz2="2" />
    <O t="0" a="0" b="0" o="1" nF="2" nB="1" nS="1" >
     <IA n="3" i0="3" i1="0" i2="2" />
     <IB n="3" i0="1" i1="3" i2="2" />
    </O>
    <DP n="1" d0="Hawaii" CU0="44" MHz0="720" FPC0="128" />
   </P>
   <ID kG0="1" kG1="1" kG2="1" b0="2" b1="2" ppdO="0" ppdLS="0" ppdAll="0" >
    <K i="0" wG0="16" wG1="16" mT0="4" mT1="4" b0="2" b1="2" nlpaA="1" lspaA="4" tspaA="4" nlpeA="1" lspeA="64" tspeA="64" nlpaB="1" lspaB="64" tspaB="64" nlpeB="1" lspeB="4" tspeB="4" u0="4" u1="1" />
   </ID>
  </S>
  <B t="9.360757" u="ms" />
 </TE>
 <TE>
  <S>
   <P>
    <TC t="0" n="3" st0="2" sz0="2463" st1="9852" sz1="2463" st2="48530952" sz2="2" />
    <TA t="0" n="3" st0="2" sz0="2463" st1="9852" sz1="2463" st2="48530952" sz2="2" />
    <TB t="0" n="3" st0="2" sz0="2463" st1="9852" sz1="2463" st2="48530952" sz2="2" />
    <O t="0" a="0" b="0" o="1" nF="2" nB="1" nS="1" >
     <IA n="3" i0="3" i1="0" i2="2" />
     <IB n="3" i0="1" i1="3" i2="2" />
    </O>
    <DP n="1" d0="Hawaii" CU0="44" MHz0="720" FPC0="128" />
   </P>
   <ID kG0="2" kG1="2" kG2="1" b0="1" b1="1" ppdO="0" ppdLS="0" ppdAll="0" >
    <K i="0" wG0="16" wG1="16" mT0="5" mT1="5" b0="0" b1="0" nlpaA="1" lspaA="16" tspaA="16" nlpeA="5" lspeA="16" tspeA="80" nlpaB="5" lspaB="16" tspaB="80" nlpeB="1" lspeB="16" tspeB="16" u0="16" u1="1" />
    <K i="1" wG0="16" wG1="16" mT0="5" mT1="5" b0="1" b1="0" nlpaA="1" lspaA="16" tspaA="16" nlpeA="5" lspeA="16" tspeA="80" nlpaB="5" lspaB="16" tspaB="80" nlpeB="1" lspeB="16" tspeB="16" u0="16" u1="1" />
    <K i="2" wG0="16" wG1="16" mT0="5" mT1="5" b0="0" b1="1" nlpaA="1" lspaA="16" tspaA="16" nlpeA="5" lspeA="16" tspeA="80" nlpaB="5" lspaB="16" tspaB="80" nlpeB="1" lspeB="16" tspeB="16" u0="16" u1="1" />
    <K i="3" wG0="16" wG1="16" mT0="5" mT1="5" b0="1" b1="1" nlpaA="1" lspaA="16" tspaA="16" nlpeA="5" lspeA="16" tspeA="80" nlpaB="5" lspaB="16" tspaB="80" nlpeB="1" lspeB="16" tspeB="16" u0="16" u1="1" />
   </ID>
  </S>
  <B t="24.335914" u="ms" />
 </TE>
 <TE>
  <S>
   <P>
    <TC t="0" n="3" st0="2" sz0="1472" st1="5888" sz1="1472" st2="17334272" sz2="2" />
    <TA t="0" n="3" st0="2" sz0="1471" st1="5884" sz1="1472" st2="17322496" sz2="2" />
    <TB t="0" n="3" st0="2" sz0="1472" st1="5888" sz1="1471" st2="17322496" sz2="2" />
    <O t="0" a="0" b="0" o="1" nF="2" nB="1" nS="1" >
     <IA n="3" i0="3" i1="0" i2="2" />
     <IB n="3" i0="1" i1="3" i2="2" />
    </O>
    <DP n="1" d0="Hawaii" CU0="44" MHz0="720" FPC0="128" />
   </P>
   <ID kG0="2" kG1="2" kG2="1" b0="1" b1="1" ppdO="0" ppdLS="0" ppdAll="0" >
    <K i="0" wG0="16" wG1="16" mT0="4" mT1="4" b0="0" b1="0" nlpaA="1" lspaA="8" tspaA="8" nlpeA="2" lspeA="32" tspeA="64" nlpaB="2" lspaB="32" tspaB="64" nlpeB="1" lspeB="8" tspeB="8" u0="8" u1="1" />
    <K i="1" wG0="16" wG1="16" mT0="4" mT1="4" b0="1" b1="0" nlpaA="1" lspaA="8" tspaA="8" nlpeA="2" lspeA="32" tspeA="64" nlpaB="2" lspaB="32" tspaB="64" nlpeB="1" lspeB="8" tspeB="8" u0="8" u1="1" />
    <K i="2" wG0="16" wG1="16" mT0="4" mT1="4" b0="0" b1="1" nlpaA="1" lspaA="8" tspaA="8" nlpeA="2" lspeA="32" tspeA="64" nlpaB="2" lspaB="32" tspaB="64" nlpeB="1" lspeB="8" tspeB="8" u0="8" u1="1" />
    <K i="3" wG0="16" wG1="16" mT0="4" mT1="4" b0="1" b1="1" nlpaA="1" lspaA="8" tspaA="8" nlpeA="2" lspeA="32" tspeA="64" nlpaB="2" lspaB="32" tspaB="64" nlpeB="1" lspeB="8" tspeB="8" u0="8" u1="1" />
   </ID>
  </S>
  <B t="4.835112" u="ms" />
 </TE>
 <TE>
  <S>
   <P>
    <TC t="0" n="3" st0="2" sz0="736" st1="2944" sz1="736" st2="4333568" sz2="2" />
    <TA t="0" n="3" st0="2" sz0="736" st1="2944" sz1="736" st2="4333568" sz2="2" />
    <TB t="0" n="3" st0="2" sz0="736" st1="2944" sz1="736" st2="4333568" sz2="2" />
    <O t="0" a="0" b="0" o="1" nF="2" nB="1" nS="1" >
     <IA n="3" i0="3" i1="0" i2="2" />
     <IB n="3" i0="1" i1="3" i2="2" />
    </O>
    <DP n="1" d0="Hawaii" CU0="44" MHz0="720" FPC0="128" />
   </P>
   <ID kG0="1" kG1="1" kG2="1" b0="2" b1="2" ppdO="0" ppdLS="0" ppdAll="0" >
    <K i="0" wG0="16" wG1="16" mT0="6" mT1="6" b0="2" b1="2" nlpaA="1" lspaA="4" tspaA="4" nlpeA="2" lspeA="64" tspeA="96" nlpaB="1" lspaB="96" tspaB="96" nlpeB="2" lspeB="2" tspeB="4" u0="4" u1="0" />
   </ID>
  </S>
  <B t="0.978756" u="ms" />
 </TE>
 <TE>
  <S>
   <P>
    <TC t="0" n="3" st0="2" sz0="16" st1="64" sz1="16" st2="2048" sz2="2" />
    <TA t="0" n="3" st0="2" sz0="16" st1="64" sz1="16" st2="2048" sz2="2" />
    <TB t="0" n="3" st0="2" sz0="16" st1="64" sz1="16" st2="2048" sz2="2" />
    <O t="0" a="0" b="0" o="1" nF="2" nB="1" nS="1" >
     <IA n="3" i0="3" i1="0" i2="2" />
     <IB n="3" i0="1" i1="3" i2="2" />
    </O>
    <DP n="1" d0="Hawaii" CU0="44" MHz0="720" FPC0="128" />
   </P>
   <ID kG0="2" kG1="2" kG2="1" b0="1" b1="1" ppdO="0" ppdLS="0" ppdAll="0" >
    <K i="0" wG0="8" wG1="8" mT0="2" mT1="2" b0="0" b1="0" nlpaA="1" lspaA="16" tspaA="16" nlpeA="4" lspeA="4" tspeA="16" nlpaB="4" lspaB="4" tspaB="16" nlpeB="1" lspeB="16" tspeB="16" u0="16" u1="0" />
    <K i="1" wG0="8" wG1="8" mT0="2" mT1="2" b0="1" b1="0" nlpaA="1" lspaA="16" tspaA="16" nlpeA="4" lspeA="4" tspeA="16" nlpaB="4" lspaB="4" tspaB="16" nlpeB="1" lspeB="16" tspeB="16" u0="16" u1="0" />
    <K i="2" wG0="8" wG1="8" mT0="2" mT1="2" b0="0" b1="1" nlpaA="1" lspaA="16" tspaA="16" nlpeA="4" lspeA="4" tspeA="16" nlpaB="4" lspaB="4" tspaB="16" nlpeB="1" lspeB="16" tspeB="16" u0="16" u1="0" />
    <K i="3" wG0="8" wG1="8" mT0="2" mT1="2" b0="1" b1="1" nlpaA="1" lspaA="16" tspaA="16" nlpeA="4" lspeA="4" tspeA="16" nlpaB="4" lspaB="4" tspaB="16" nlpeB="1" lspeB="16" tspeB="16" u0="16" u1="0" />
   </ID>
  </S>
  <B t="0.112444" u="ms" />
 </TE>
 <TE>
  <S>
   <P>
    <TC t="0" n="3" st0="2" sz0="1936" st1="7744" sz1="1936" st2="29984768" sz2="2" />
    <TA t="0" n="3" st0="2" sz0="1936" st1="7744" sz1="1936" st2="29984768" sz2="2" />
    <TB t="0" n="3" st0="2" sz0="1936" st1="7744" sz1="1936" st2="29984768" sz2="2" />
    <O t="0" a="0" b="0" o="1" nF="2" nB="1" nS="1" >
     <IA n="3" i0="3" i1="0" i2="2" />
     <IB n="3" i0="1" i1="3" i2="2" />
    </O>
    <DP n="1" d0="Hawaii" CU0="44" MHz0="720" FPC0="128" />
   </P>
   <ID kG0="1" kG1="1" kG2="1" b0="2" b1="2" ppdO="0" ppdLS="0" ppdAll="0" >
    <K i="0" wG0="16" wG1="16" mT0="5" mT1="5" b0="2" b1="2" nlpaA="1" lspaA="16" tspaA="16" nlpeA="5" lspeA="16" tspeA="80" nlpaB="5" lspaB="16" tspaB="80" nlpeB="1" lspeB="16" tspeB="16" u0="16" u1="0" />
   </ID>
  </S>
  <B t="11.258624" u="ms" />
 </TE>
 <TE>
  <S>
   <P>
    <TC t="0" n="3" st0="2" sz0="1071" st1="4284" sz1="1071" st2="9176328" sz2="2" />
    <TA t="0" n="3" st0="2" sz0="1071" st1="4284" sz1="1071" st2="9176328" sz2="2" />
    <TB t="0" n="3" st0="2" sz0="1071" st1="4284" sz1="1071" st2="9176328" sz2="2" />
    <O t="0" a="0" b="0" o="1" nF="2" nB="1" nS="1" >
     <IA n="3" i0="3" i1="0" i2="2" />
     <IB n="3" i0="1" i1="3" i2="2" />
    </O>
    <DP n="1" d0="Hawaii" CU0="44" MHz0="720" FPC0="128" />
   </P>
   <ID kG0="1" kG1="1" kG2="1" b0="2" b1="2" ppdO="0" ppdLS="0" ppdAll="0" >
    <K i="0" wG0="16" wG1="16" mT0="5" mT1="5" b0="2" b1="2" nlpaA="1" lspaA="16" tspaA="16" nlpeA="5" lspeA="16" tspeA="80" nlpaB="5" lspaB="16" tspaB="80" nlpeB="1" lspeB="16" tspeB="16" u0="16" u1="1" />
   </ID>
  </S>
  <B t="2.741200" u="ms" />
 </TE>
 <TE>
  <S>
   <P>
    <TC t="0" n="3" st0="2" sz0="736" st1="2944" sz1="736" st2="4333568" sz2="2" />
    <TA t="0" n="3" st0="2" sz0="736" st1="2944" sz1="736" st2="4333568" sz2="2" />
    <TB t="0" n="3" st0="2" sz0="736" st1="2944" sz1="736" st2="4333568" sz2="2" />
    <O t="0" a="0" b="0" o="1" nF="2" nB="1" nS="1" >
     <IA n="3" i0="3" i1="0" i2="2" />
     <IB n="3" i0="1" i1="3" i2="2" />
    </O>
    <DP n="1" d0="Hawaii" CU0="44" MHz0="720" FPC0="128" />
   </P>
   <ID kG0="1" kG1="1" kG2="1" b0="2" b1="2" ppdO="0" ppdLS="0" ppdAll="0" >
    <K i="0" wG0="16" wG1="16" mT0="6" mT1="6" b0="2" b1="2" nlpaA="1" lspaA="16" tspaA="16" nlpeA="6" lspeA="16" tspeA="96" nlpaB="6" lspaB="16" tspaB="96" nlpeB="1" lspeB="16" tspeB="16" u0="16" u1="0" />
   </ID>
  </S>
  <B t="0.871200" u="ms" />
 </TE>
 <TE>
  <S>
   <P>
    <TC t="0" n="3" st0="2" sz0="1936" st1="7744" sz1="1936" st2="29984768" sz2="2" />
    <TA t="0" n="3" st0="2" sz0="1936" st1="7744" sz1="1936" st2="29984768" sz2="2" />
    <TB t="0" n="3" st0="2" sz0="1936" st1="7744" sz1="1936" st2="29984768" sz2="2" />
    <O t="0" a="0" b="0" o="1" nF="2" nB="1" nS="1" >
     <IA n="3" i0="3" i1="0" i2="2" />
     <IB n="3" i0="1" i1="3" i2="2" />
    </O>
    <DP n="1" d0="Hawaii" CU0="44" MHz0="720" FPC0="128" />
   </P>
   <ID kG0="1" kG1="1" kG2="1" b0="2" b1="2" ppdO="0" ppdLS="0" ppdAll="0" >
    <K i="0" wG0="16" wG1="16" mT0="6" mT1="6" b0="2" b1="2" nlpaA="1" lspaA="16" tspaA="16" nlpeA="6" lspeA="16" tspeA="96" nlpaB="6" lspaB="16" tspaB="96" nlpeB="1" lspeB="16" tspeB="16" u0="16" u1="0" />
   </ID>
  </S>
  <B t="11.811068" u="ms" />
 </TE>
 <TE>
  <S>
   <P>
    <TC t="0" n="3" st0="2" sz0="15" st1="60" sz1="15" st2="1800" sz2="2" />
    <TA t="0" n="3" st0="2" sz0="15" st1="60" sz1="15" st2="1800" sz2="2" />
    <TB t="0" n="3" st0="2" sz0="15" st1="60" sz1="15" st2="1800" sz2="2" />
    <O t="0" a="0" b="0" o="1" nF="2" nB="1" nS="1" >
     <IA n="3" i0="3" i1="0" i2="2" />
     <IB n="3" i0="1" i1="3" i2="2" />
    </O>
    <DP n="1" d0="Hawaii" CU0="44" MHz0="720" FPC0="128" />
   </P>
   <ID kG0="1" kG1="1" kG2="1" b0="2" b1="2" ppdO="0" ppdLS="0" ppdAll="0" >
    <K i="0" wG0="16" wG1="16" mT0="3" mT1="3" b0="2" b1="2" nlpaA="1" lspaA="8" tspaA="8" nlpeA="2" lspeA="32" tspeA="48" nlpaB="1" lspaB="48" tspaB="48" nlpeB="2" lspeB="5" tspeB="8" u0="8" u1="1" />
   </ID>
  </S>
  <B t="0.105600" u="ms" />
 </TE>
 <TE>
  <S>
   <P>
    <TC t="0" n="3" st0="2" sz0="895" st1="3580" sz1="895" st2="6408200" sz2="2" />
    <TA t="0" n="3" st0="2" sz0="895" st1="3580" sz1="895" st2="6408200" sz2="2" />
    <TB t="0" n="3" st0="2" sz0="895" st1="3580" sz1="895" st2="6408200" sz2="2" />
    <O t="0" a="0" b="0" o="1" nF="2" nB="1" nS="1" >
     <IA n="3" i0="3" i1="0" i2="2" />
     <IB n="3" i0="1" i1="3" i2="2" />
    </O>
    <DP n="1" d0="Hawaii" CU0="44" MHz0="720" FPC0="128" />
   </P>
   <ID kG0="1" kG1="1" kG2="1" b0="2" b1="2" ppdO="0" ppdLS="0" ppdAll="0" >
    <K i="0" wG0="16" wG1="16" mT0="4" mT1="4" b0="2" b1="2" nlpaA="1" lspaA="8" tspaA="8" nlpeA="2" lspeA="32" tspeA="64" nlpaB="2" lspaB="32" tspaB="64" nlpeB="1" lspeB="8" tspeB="8" u0="8" u1="1" />
   </ID>
  </S>
  <B t="2.049422" u="ms" />
 </TE>
 <TE>
  <S>
   <P>
    <TC t="0" n="3" st0="2" sz0="1471" st1="5884" sz1="1471" st2="17310728" sz2="2" />
    <TA t="0" n="3" st0="2" sz0="1471" st1="5884" sz1="1471" st2="17310728" sz2="2" />
    <TB t="0" n="3" st0="2" sz0="1471" st1="5884" sz1="1471" st2="17310728" sz2="2" />
    <O t="0" a="0" b="0" o="1" nF="2" nB="1" nS="1" >
     <IA n="3" i0="3" i1="0" i2="2" />
     <IB n="3" i0="1" i1="3" i2="2" />
    </O>
    <DP n="1" d0="Hawaii" CU0="44" MHz0="720" FPC0="128" />
   </P>
   <ID kG0="1" kG1="1" kG2="1" b0="2" b1="2" ppdO="0" ppdLS="0" ppdAll="0" >
    <K i="0" wG0="16" wG1="16" mT0="5" mT1="5" b0="2" b1="2" nlpaA="1" lspaA="16" tspaA="16" nlpeA="5" lspeA="16" tspeA="80" nlpaB="5" lspaB="16" tspaB="80" nlpeB="1" lspeB="16" tspeB="16" u0="16" u1="1" />
   </ID>
  </S>
  <B t="6.525201" u="ms" />
 </TE>
 <TE>
  <S>
   <P>
    <TC t="0" n="3" st0="2" sz0="736" st1="2944" sz1="736" st2="4333568" sz2="2" />
    <TA t="0" n="3" st0="2" sz0="736" st1="2944" sz1="736" st2="4333568" sz2="2" />
    <TB t="0" n="3" st0="2" sz0="736" st1="2944" sz1="736" st2="4333568" sz2="2" />
    <O t="0" a="0" b="0" o="1" nF="2" nB="1" nS="1" >
     <IA n="3" i0="3" i1="0" i2="2" />
     <IB n="3" i0="1" i1="3" i2="2" />
    </O>
    <DP n="1" d0="Hawaii" CU0="44" MHz0="720" FPC0="128" />
   </P>
   <ID kG0="1" kG1="1" kG2="1" b0="2" b1="2" ppdO="0" ppdLS="0" ppdAll="0" >
    <K i="0" wG0="16" wG1="16" mT0="6" mT1="6" b0="2" b1="2" nlpaA="1" lspaA="8" tspaA="8" nlpeA="3" lspeA="32" tspeA="96" nlpaB="3" lspaB="32" tspaB="96" nlpeB="1" lspeB="8" tspeB="8" u0="8" u1="0" />
   </ID>
  </S>
  <B t="0.888311" u="ms" />
 </TE>
 <TE>
  <S>
   <P>
    <TC t="0" n="3" st0="2" sz0="1472" st1="5888" sz1="1472" st2="17334272" sz2="2" />
    <TA t="0" n="3" st0="2" sz0="1472" st1="5888" sz1="1472" st2="17334272" sz2="2" />
    <TB t="0" n="3" st0="2" sz0="1472" st1="5888" sz1="1472" st2="17334272" sz2="2" />
    <O t="0" a="0" b="0" o="1" nF="2" nB="1" nS="1" >
     <IA n="3" i0="3" i1="0" i2="2" />
     <IB n="3" i0="1" i1="3" i2="2" />
    </O>
    <DP n="1" d0="Hawaii" CU0="44" MHz0="720" FPC0="128" />
   </P>
   <ID kG0="1" kG1="1" kG2="1" b0="2" b1="2" ppdO="0" ppdLS="0" ppdAll="0" >
    <K i="0" wG0="16" wG1="16" mT0="7" mT1="7" b0="2" b1="2" nlpaA="1" lspaA="4" tspaA="4" nlpeA="2" lspeA="64" tspeA="112" nlpaB="1" lspaB="112" tspaB="112" nlpeB="2" lspeB="2" tspeB="4" u0="4" u1="0" />
   </ID>
  </S>
  <B t="6.110134" u="ms" />
 </TE>
 <TE>
  <S>
   <P>
    <TC t="0" n="3" st0="2" sz0="111" st1="444" sz1="111" st2="98568" sz2="2" />
    <TA t="0" n="3" st0="2" sz0="111" st1="444" sz1="111" st2="98568" sz2="2" />
    <TB t="0" n="3" st0="2" sz0="111" st1="444" sz1="111" st2="98568" sz2="2" />
    <O t="0" a="0" b="0" o="1" nF="2" nB="1" nS="1" >
     <IA n="3" i0="3" i1="0" i2="2" />
     <IB n="3" i0="1" i1="3" i2="2" />
    </O>
    <DP n="1" d0="Hawaii" CU0="44" MHz0="720" FPC0="128" />
   </P>
   <ID kG0="1" kG1="1" kG2="1" b0="2" b1="2" ppdO="0" ppdLS="0" ppdAll="0" >
    <K i="0" wG0="16" wG1="16" mT0="2" mT1="2" b0="2" b1="2" nlpaA="1" lspaA="8" tspaA="8" nlpeA="1" lspeA="32" tspeA="32" nlpaB="1" lspaB="32" tspaB="32" nlpeB="1" lspeB="8" tspeB="8" u0="8" u1="1" />
   </ID>
  </S>
  <B t="0.173556" u="ms" />
 </TE>
 <TE>
  <S>
   <P>
    <TC t="0" n="3" st0="2" sz0="1472" st1="5888" sz1="1472" st2="17334272" sz2="2" />
    <TA t="0" n="3" st0="2" sz0="1472" st1="5888" sz1="1472" st2="17334272" sz2="2" />
    <TB t="0" n="3" st0="2" sz0="1472" st1="5888" sz1="1472" st2="17334272" sz2="2" />
    <O t="0" a="0" b="0" o="1" nF="2" nB="1" nS="1" >
     <IA n="3" i0="3" i1="0" i2="2" />
     <IB n="3" i0="1" i1="3" i2="2" />
    </O>
    <DP n="1" d0="Hawaii" CU0="44" MHz0="720" FPC0="128" />
   </P>
   <ID kG0="1" kG1="1" kG2="1" b0="2" b1="2" ppdO="0" ppdLS="0" ppdAll="0" >
    <K i="0" wG0="16" wG1="16" mT0="6" mT1="6" b0="2" b1="2" nlpaA="1" lspaA="16" tspaA="16" nlpeA="6" lspeA="16" tspeA="96" nlpaB="6" lspaB="16" tspaB="96" nlpeB="1" lspeB="16" tspeB="16" u0="16" u1="0" />
   </ID>
  </S>
  <B t="5.587512" u="ms" />
 </TE>
 <TE>
  <S>
   <P>
    <TC t="0" n="3" st0="2" sz0="1072" st1="4288" sz1="1072" st2="9193472" sz2="2" />
    <TA t="0" n="3" st0="2" sz0="1071" st1="4284" sz1="1072" st2="9184896" sz2="2" />
    <TB t="0" n="3" st0="2" sz0="1072" st1="4288" sz1="1071" st2="9184896" sz2="2" />
    <O t="0" a="0" b="0" o="1" nF="2" nB="1" nS="1" >
     <IA n="3" i0="3" i1="0" i2="2" />
     <IB n="3" i0="1" i1="3" i2="2" />
    </O>
    <DP n="1" d0="Hawaii" CU0="44" MHz0="720" FPC0="128" />
   </P>
   <ID kG0="1" kG1="1" kG2="1" b0="2" b1="2" ppdO="0" ppdLS="0" ppdAll="0" >
    <K i="0" wG0="16" wG1="16" mT0="8" mT1="8" b0="2" b1="2" nlpaA="1" lspaA="4" tspaA="4" nlpeA="2" lspeA="64" tspeA="128" nlpaB="2" lspaB="64" tspaB="128" nlpeB="1" lspeB="4" tspeB="4" u0="4" u1="1" />
   </ID>
  </S>
  <B t="2.881023" u="ms" />
 </TE>
 <TE>
  <S>
   <P>
    <TC t="0" n="3" st0="2" sz0="896" st1="3584" sz1="896" st2="6422528" sz2="2" />
    <TA t="0" n="3" st0="2" sz0="895" st1="3580" sz1="896" st2="6415360" sz2="2" />
    <TB t="0" n="3" st0="2" sz0="896" st1="3584" sz1="895" st2="6415360" sz2="2" />
    <O t="0" a="0" b="0" o="1" nF="2" nB="1" nS="1" >
     <IA n="3" i0="3" i1="0" i2="2" />
     <IB n="3" i0="1" i1="3" i2="2" />
    </O>
    <DP n="1" d0="Hawaii" CU0="44" MHz0="720" FPC0="128" />
   </P>
   <ID kG0="2" kG1="2" kG2="1" b0="1" b1="1" ppdO="0" ppdLS="0" ppdAll="0" >
    <K i="0" wG0="16" wG1="16" mT0="4" mT1="4" b0="0" b1="0" nlpaA="1" lspaA="16" tspaA="16" nlpeA="4" lspeA="16" tspeA="64" nlpaB="4" lspaB="16" tspaB="64" nlpeB="1" lspeB="16" tspeB="16" u0="16" u1="1" />
    <K i="1" wG0="16" wG1="16" mT0="4" mT1="4" b0="1" b1="0" nlpaA="1" lspaA="16" tspaA="16" nlpeA="4" lspeA="16" tspeA="64" nlpaB="4" lspaB="16" tspaB="64" nlpeB="1" lspeB="16" tspeB="16" u0="16" u1="1" />
    <K i="2" wG0="16" wG1="16" mT0="4" mT1="4" b0="0" b1="1" nlpaA="1" lspaA="16" tspaA="16" nlpeA="4" lspeA="16" tspeA="64" nlpaB="4" lspaB="16" tspaB="64" nlpeB="1" lspeB="16" tspeB="16" u0="16" u1="1" />
    <K i="3" wG0="16" wG1="16" mT0="4" mT1="4" b0="1" b1="1" nlpaA="1" lspaA="16" tspaA="16" nlpeA="4" lspeA="16" tspeA="64" nlpaB="4" lspaB="16" tspaB="64" nlpeB="1" lspeB="16" tspeB="16" u0="16" u1="1" />
   </ID>
  </S>
  <B t="1.723334" u="ms" />
 </TE>
 <TE>
  <S>
   <P>
    <TC t="0" n="3" st0="2" sz0="592" st1="2368" sz1="592" st2="2803712" sz2="2" />
    <TA t="0" n="3" st0="2" sz0="591" st1="2364" sz1="592" st2="2798976" sz2="2" />
    <TB t="0" n="3" st0="2" sz0="592" st1="2368" sz1="591" st2="2798976" sz2="2" />
    <O t="0" a="0" b="0" o="1" nF="2" nB="1" nS="1" >
     <IA n="3" i0="3" i1="0" i2="2" />
     <IB n="3" i0="1" i1="3" i2="2" />
    </O>
    <DP n="1" d0="Hawaii" CU0="44" MHz0="720" FPC0="128" />
   </P>
   <ID kG0="1" kG1="1" kG2="1" b0="2" b1="2" ppdO="0" ppdLS="0" ppdAll="0" >
    <K i="0" wG0="16" wG1="16" mT0="5" mT1="5" b0="2" b1="2" nlpaA="1" lspaA="16" tspaA="16" nlpeA="5" lspeA="16" tspeA="80" nlpaB="5" lspaB="16" tspaB="80" nlpeB="1" lspeB="16" tspeB="16" u0="16" u1="1" />
   </ID>
  </S>
  <B t="0.567600" u="ms" />
 </TE>
 <TE>
  <S>
   <P>
    <TC t="0" n="3" st0="2" sz0="351" st1="1404" sz1="351" st2="985608" sz2="2" />
    <TA t="0" n="3" st0="2" sz0="351" st1="1404" sz1="351" st2="985608" sz2="2" />
    <TB t="0" n="3" st0="2" sz0="351" st1="1404" sz1="351" st2="985608" sz2="2" />
    <O t="0" a="0" b="0" o="1" nF="2" nB="1" nS="1" >
     <IA n="3" i0="3" i1="0" i2="2" />
     <IB n="3" i0="1" i1="3" i2="2" />
    </O>
    <DP n="1" d0="Hawaii" CU0="44" MHz0="720" FPC0="128" />
   </P>
   <ID kG0="1" kG1="1" kG2="1" b0="2" b1="2" ppdO="0" ppdLS="0" ppdAll="0" >
    <K i="0" wG0="16" wG1="16" mT0="3" mT1="3" b0="2" b1="2" nlpaA="1" lspaA="16" tspaA="16" nlpeA="3" lspeA="16" tspeA="48" nlpaB="3" lspaB="16" tspaB="48" nlpeB="1" lspeB="16" tspeB="16" u0="16" u1="1" />
   </ID>
  </S>
  <B t="0.251289" u="ms" />
 </TE>
 <TE>
  <S>
   <P>
    <TC t="0" n="3" st0="2" sz0="31" st1="124" sz1="31" st2="7688" sz2="2" />
    <TA t="0" n="3" st0="2" sz0="32" st1="128" sz1="31" st2="7936" sz2="2" />
    <TB t="0" n="3" st0="2" sz0="31" st1="124" sz1="32" st2="7936" sz2="2" />
    <O t="0" a="0" b="0" o="1" nF="2" nB="1" nS="1" >
     <IA n="3" i0="3" i1="0" i2="2" />
     <IB n="3" i0="1" i1="3" i2="2" />
    </O>
    <DP n="1" d0="Hawaii" CU0="44" MHz0="720" FPC0="128" />
   </P>
   <ID kG0="1" kG1="1" kG2="1" b0="2" b1="2" ppdO="0" ppdLS="0" ppdAll="0" >
    <K i="0" wG0="16" wG1="16" mT0="2" mT1="2" b0="2" b1="2" nlpaA="1" lspaA="4" tspaA="4" nlpeA="1" lspeA="32" tspeA="32" nlpaB="1" lspaB="32" tspaB="32" nlpeB="1" lspeB="4" tspeB="4" u0="4" u1="0" />
   </ID>
  </S>
  <B t="0.129556" u="ms" />
 </TE>
 <TE>
  <S>
   <P>
    <TC t="0" n="3" st0="2" sz0="2464" st1="9856" sz1="2464" st2="48570368" sz2="2" />
    <TA t="0" n="3" st0="2" sz0="2463" st1="9852" sz1="2464" st2="48550656" sz2="2" />
    <TB t="0" n="3" st0="2" sz0="2464" st1="9856" sz1="2463" st2="48550656" sz2="2" />
    <O t="0" a="0" b="0" o="1" nF="2" nB="1" nS="1" >
     <IA n="3" i0="3" i1="0" i2="2" />
     <IB n="3" i0="1" i1="3" i2="2" />
    </O>
    <DP n="1" d0="Hawaii" CU0="44" MHz0="720" FPC0="128" />
   </P>
   <ID kG0="2" kG1="2" kG2="1" b0="1" b1="1" ppdO="0" ppdLS="0" ppdAll="0" >
    <K i="0" wG0="16" wG1="16" mT0="5" mT1="5" b0="0" b1="0" nlpaA="1" lspaA="16" tspaA="16" nlpeA="5" lspeA="16" tspeA="80" nlpaB="5" lspaB="16" tspaB="80" nlpeB="1" lspeB="16" tspeB="16" u0="16" u1="1" />
    <K i="1" wG0="16" wG1="16" mT0="5" mT1="5" b0="1" b1="0" nlpaA="1" lspaA="16" tspaA="16" nlpeA="5" lspeA="16" tspeA="80" nlpaB="5" lspaB="16" tspaB="80" nlpeB="1" lspeB="16" tspeB="16" u0="16" u1="1" />
    <K i="2" wG0="16" wG1="16" mT0="5" mT1="5" b0="0" b1="1" nlpaA="1" lspaA="16" tspaA="16" nlpeA="5" lspeA="16" tspeA="80" nlpaB="5" lspaB="16" tspaB="80" nlpeB="1" lspeB="16" tspeB="16" u0="16" u1="1" />
    <K i="3" wG0="16" wG1="16" mT0="5" mT1="5" b0="1" b1="1" nlpaA="1" lspaA="16" tspaA="16" nlpeA="5" lspeA="16" tspeA="80" nlpaB="5" lspaB="16" tspaB="80" nlpeB="1" lspeB="16" tspeB="16" u0="16" u1="1" />
   </ID>
  </S>
  <B t="24.634625" u="ms" />
 </TE>
 <TE>
  <S>
   <P>
    <TC t="0" n="3" st0="2" sz0="736" st1="2944" sz1="736" st2="4333568" sz2="2" />
    <TA t="0" n="3" st0="2" sz0="735" st1="2940" sz1="736" st2="4327680" sz2="2" />
    <TB t="0" n="3" st0="2" sz0="736" st1="2944" sz1="735" st2="4327680" sz2="2" />
    <O t="0" a="0" b="0" o="1" nF="2" nB="1" nS="1" >
     <IA n="3" i0="3" i1="0" i2="2" />
     <IB n="3" i0="1" i1="3" i2="2" />
    </O>
    <DP n="1" d0="Hawaii" CU0="44" MHz0="720" FPC0="128" />
   </P>
   <ID kG0="1" kG1="1" kG2="1" b0="2" b1="2" ppdO="0" ppdLS="0" ppdAll="0" >
    <K i="0" wG0="16" wG1="16" mT0="4" mT1="4" b0="2" b1="2" nlpaA="1" lspaA="8" tspaA="8" nlpeA="2" lspeA="32" tspeA="64" nlpaB="2" lspaB="32" tspaB="64" nlpeB="1" lspeB="8" tspeB="8" u0="8" u1="1" />
   </ID>
  </S>
  <B t="1.367422" u="ms" />
 </TE>
 <TE>
  <S>
   <P>
    <TC t="0" n="3" st0="2" sz0="31" st1="124" sz1="31" st2="7688" sz2="2" />
    <TA t="0" n="3" st0="2" sz0="31" st1="124" sz1="31" st2="7688" sz2="2" />
    <TB t="0" n="3" st0="2" sz0="31" st1="124" sz1="31" st2="7688" sz2="2" />
    <O t="0" a="0" b="0" o="1" nF="2" nB="1" nS="1" >
     <IA n="3" i0="3" i1="0" i2="2" />
     <IB n="3" i0="1" i1="3" i2="2" />
    </O>
    <DP n="1" d0="Hawaii" CU0="44" MHz0="720" FPC0="128" />
   </P>
   <ID kG0="1" kG1="1" kG2="1" b0="2" b1="2" ppdO="0" ppdLS="0" ppdAll="0" >
    <K i="0" wG0="16" wG1="16" mT0="2" mT1="2" b0="2" b1="2" nlpaA="1" lspaA="8" tspaA="8" nlpeA="1" lspeA="32" tspeA="32" nlpaB="1" lspaB="32" tspaB="32" nlpeB="1" lspeB="8" tspeB="8" u0="8" u1="1" />
   </ID>
  </S>
  <B t="0.197022" u="ms" />
 </TE>
 <TE>
  <S>
   <P>
    <TC t="0" n="3" st0="2" sz0="463" st1="1852" sz1="463" st2="1714952" sz2="2" />
    <TA t="0" n="3" st0="2" sz0="463" st1="1852" sz1="463" st2="1714952" sz2="2" />
    <TB t="0" n="3" st0="2" sz0="463" st1="1852" sz1="463" st2="1714952" sz2="2" />
    <O t="0" a="0" b="0" o="1" nF="2" nB="1" nS="1" >
     <IA n="3" i0="3" i1="0" i2="2" />
     <IB n="3" i0="1" i1="3" i2="2" />
    </O>
    <DP n="1" d0="Hawaii" CU0="44" MHz0="720" FPC0="128" />
   </P>
   <ID kG0="1" kG1="1" kG2="1" b0="2" b1="2" ppdO="0" ppdLS="0" ppdAll="0" >
    <K i="0" wG0="16" wG1="16" mT0="4" mT1="4" b0="2" b1="2" nlpaA="1" lspaA="8" tspaA="8" nlpeA="2" lspeA="32" tspeA="64" nlpaB="2" lspaB="32" tspaB="64" nlpeB="1" lspeB="8" tspeB="8" u0="8" u1="1" />
   </ID>
  </S>
  <B t="0.380844" u="ms" />
 </TE>
 <TE>
  <S>
   <P>
    <TC t="0" n="3" st0="2" sz0="2751" st1="11004" sz1="2751" st2="60544008" sz2="2" />
    <TA t="0" n="3" st0="2" sz0="2751" st1="11004" sz1="2751" st2="60544008" sz2="2" />
    <TB t="0" n="3" st0="2" sz0="2751" st1="11004" sz1="2751" st2="60544008" sz2="2" />
    <O t="0" a="0" b="0" o="1" nF="2" nB="1" nS="1" >
     <IA n="3" i0="3" i1="0" i2="2" />
     <IB n="3" i0="1" i1="3" i2="2" />
    </O>
    <DP n="1" d0="Hawaii" CU0="44" MHz0="720" FPC0="128" />
   </P>
   <ID kG0="2" kG1="2" kG2="1" b0="1" b1="1" ppdO="0" ppdLS="0" ppdAll="0" >
    <K i="0" wG0="16" wG1="16" mT0="5" mT1="5" b0="0" b1="0" nlpaA="1" lspaA="16" tspaA="16" nlpeA="5" lspeA="16" tspeA="80" nlpaB="5" lspaB="16" tspaB="80" nlpeB="1" lspeB="16" tspeB="16" u0="16" u1="1" />
    <K i="1" wG0="16" wG1="16" mT0="5" mT1="5" b0="1" b1="0" nlpaA="1" lspaA="16" tspaA="16" nlpeA="5" lspeA="16" tspeA="80" nlpaB="5" lspaB="16" tspaB="80" nlpeB="1" lspeB="16" tspeB="16" u0="16" u1="1" />
    <K i="2" wG0="16" wG1="16" mT0="5" mT1="5" b0="0" b1="1" nlpaA="1" lspaA="16" tspaA="16" nlpeA="5" lspeA="16" tspeA="80" nlpaB="5" lspaB="16" tspaB="80" nlpeB="1" lspeB="16" tspeB="16" u0="16" u1="1" />
    <K i="3" wG0="16" wG1="16" mT0="5" mT1="5" b0="1" b1="1" nlpaA="1" lspaA="16" tspaA="16" nlpeA="5" lspeA="16" tspeA="80" nlpaB="5" lspaB="16" tspaB="80" nlpeB="1" lspeB="16" tspeB="16" u0="16" u1="1" />
   </ID>
  </S>
  <B t="33.528004" u="ms" />
 </TE>
 <TE>
  <S>
   <P>
    <TC t="0" n="3" st0="2" sz0="1696" st1="6784" sz1="1696" st2="23011328" sz2="2" />
    <TA t="0" n="3" st0="2" sz0="1696" st1="6784" sz1="1696" st2="23011328" sz2="2" />
    <TB t="0" n="3" st0="2" sz0="1696" st1="6784" sz1="1696" st2="23011328" sz2="2" />
    <O t="0" a="0" b="0" o="1" nF="2" nB="1" nS="1" >
     <IA n="3" i0="3" i1="0" i2="2" />
     <IB n="3" i0="1" i1="3" i2="2" />
    </O>
    <DP n="1" d0="Hawaii" CU0="44" MHz0="720" FPC0="128" />
   </P>
   <ID kG0="1" kG1="1" kG2="1" b0="2" b1="2" ppdO="0" ppdLS="0" ppdAll="0" >
    <K i="0" wG0="16" wG1="16" mT0="5" mT1="5" b0="2" b1="2" nlpaA="1" lspaA="16" tspaA="16" nlpeA="5" lspeA="16" tspeA="80" nlpaB="5" lspaB="16" tspaB="80" nlpeB="1" lspeB="16" tspeB="16" u0="16" u1="0" />
   </ID>
  </S>
  <B t="7.792890" u="ms" />
 </TE>
 <TE>
  <S>
   <P>
    <TC t="0" n="3" st0="2" sz0="31" st1="124" sz1="31" st2="7688" sz2="2" />
    <TA t="0" n="3" st0="2" sz0="31" st1="124" sz1="31" st2="7688" sz2="2" />
    <TB t="0" n="3" st0="2" sz0="31" st1="124" sz1="31" st2="7688" sz2="2" />
    <O t="0" a="0" b="0" o="1" nF="2" nB="1" nS="1" >
     <IA n="3" i0="3" i1="0" i2="2" />
     <IB n="3" i0="1" i1="3" i2="2" />
    </O>
    <DP n="1" d0="Hawaii" CU0="44" MHz0="720" FPC0="128" />
   </P>
   <ID kG0="1" kG1="1" kG2="1" b0="2" b1="2" ppdO="0" ppdLS="0" ppdAll="0" >
    <K i="0" wG0="8" wG1="8" mT0="2" mT1="2" b0="2" b1="2" nlpaA="1" lspaA="4" tspaA="4" nlpeA="1" lspeA="16" tspeA="16" nlpaB="1" lspaB="16" tspaB="16" nlpeB="1" lspeB="4" tspeB="4" u0="4" u1="1" />
   </ID>
  </S>
  <B t="0.158889" u="ms" />
 </TE>
 <TE>
  <S>
   <P>
    <TC t="0" n="3" st0="2" sz0="1696" st1="6784" sz1="1696" st2="23011328" sz2="2" />
    <TA t="0" n="3" st0="2" sz0="1695" st1="6780" sz1="1696" st2="22997760" sz2="2" />
    <TB t="0" n="3" st0="2" sz0="1696" st1="6784" sz1="1695" st2="22997760" sz2="2" />
    <O t="0" a="0" b="0" o="1" nF="2" nB="1" nS="1" >
     <IA n="3" i0="3" i1="0" i2="2" />
     <IB n="3" i0="1" i1="3" i2="2" />
    </O>
    <DP n="1" d0="Hawaii" CU0="44" MHz0="720" FPC0="128" />
   </P>
   <ID kG0="2" kG1="2" kG2="1" b0="1" b1="1" ppdO="0" ppdLS="0" ppdAll="0" >
    <K i="0" wG0="16" wG1="16" mT0="4" mT1="4" b0="0" b1="0" nlpaA="1" lspaA="16" tspaA="16" nlpeA="4" lspeA="16" tspeA="64" nlpaB="4" lspaB="16" tspaB="64" nlpeB="1" lspeB="16" tspeB="16" u0="16" u1="1" />
    <K i="1" wG0="16" wG1="16" mT0="4" mT1="4" b0="1" b1="0" nlpaA="1" lspaA="16" tspaA="16" nlpeA="4" lspeA="16" tspeA="64" nlpaB="4" lspaB="16" tspaB="64" nlpeB="1" lspeB="16" tspeB="16" u0="16" u1="1" />
    <K i="2" wG0="16" wG1="16" mT0="4" mT1="4" b0="0" b1="1" nlpaA="1" lspaA="16" tspaA="16" nlpeA="4" lspeA="16" tspeA="64" nlpaB="4" lspaB="16" tspaB="64" nlpeB="1" lspeB="16" tspeB="16" u0="16" u1="1" />
    <K i="3" wG0="16" wG1="16" mT0="4" mT1="4" b0="1" b1="1" nlpaA="1" lspaA="16" tspaA="16" nlpeA="4" lspeA="16" tspeA="64" nlpaB="4" lspaB="16" tspaB="64" nlpeB="1" lspeB="16" tspeB="16" u0="16" u1="1" />
   </ID>
  </S>
  <B t="8.782401" u="ms" />
 </TE>
 <TE>
  <S>
   <P>
    <TC t="0" n="3" st0="2" sz0="592" st1="2368" sz1="592" st2="2803712" sz2="2" />
    <TA t="0" n="3" st0="2" sz0="591" st1="2364" sz1="592" st2="2798976" sz2="2" />
    <TB t="0" n="3" st0="2" sz0="592" st1="2368" sz1="591" st2="2798976" sz2="2" />
    <O t="0" a="0" b="0" o="1" nF="2" nB="1" nS="1" >
     <IA n="3" i0="3" i1="0" i2="2" />
     <IB n="3" i0="1" i1="3" i2="2" />
    </O>
    <DP n="1" d0="Hawaii" CU0="44" MHz0="720" FPC0="128" />
   </P>
   <ID kG0="1" kG1="1" kG2="1" b0="2" b1="2" ppdO="0" ppdLS="0" ppdAll="0" >
    <K i="0" wG0="16" wG1="16" mT0="8" mT1="8" b0="2" b1="2" nlpaA="1" lspaA="8" tspaA="8" nlpeA="4" lspeA="32" tspeA="128" nlpaB="4" lspaB="32" tspaB="128" nlpeB="1" lspeB="8" tspeB="8" u0="8" u1="1" />
   </ID>
  </S>
  <B t="0.793467" u="ms" />
 </TE>
 <TE>
  <S>
   <P>
    <TC t="0" n="3" st0="2" sz0="463" st1="1852" sz1="463" st2="1714952" sz2="2" />
    <TA t="0" n="3" st0="2" sz0="464" st1="1856" sz1="463" st2="1718656" sz2="2" />
    <TB t="0" n="3" st0="2" sz0="463" st1="1852" sz1="464" st2="1718656" sz2="2" />
    <O t="0" a="0" b="0" o="1" nF="2" nB="1" nS="1" >
     <IA n="3" i0="3" i1="0" i2="2" />
     <IB n="3" i0="1" i1="3" i2="2" />
    </O>
    <DP n="1" d0="Hawaii" CU0="44" MHz0="720" FPC0="128" />
   </P>
   <ID kG0="1" kG1="1" kG2="1" b0="2" b1="2" ppdO="0" ppdLS="0" ppdAll="0" >
    <K i="0" wG0="16" wG1="16" mT0="3" mT1="3" b0="2" b1="2" nlpaA="1" lspaA="16" tspaA="16" nlpeA="3" lspeA="16" tspeA="48" nlpaB="3" lspaB="16" tspaB="48" nlpeB="1" lspeB="16" tspeB="16" u0="16" u1="0" />
   </ID>
  </S>
  <B t="0.359822" u="ms" />
 </TE>
 <TE>
  <S>
   <P>
    <TC t="0" n="3" st0="2" sz0="15" st1="60" sz1="15" st2="1800" sz2="2" />
    <TA t="0" n="3" st0="2" sz0="15" st1="60" sz1="15" st2="1800" sz2="2" />
    <TB t="0" n="3" st0="2" sz0="15" st1="60" sz1="15" st2="1800" sz2="2" />
    <O t="0" a="0" b="0" o="1" nF="2" nB="1" nS="1" >
     <IA n="3" i0="3" i1="0" i2="2" />
     <IB n="3" i0="1" i1="3" i2="2" />
    </O>
    <DP n="1" d0="Hawaii" CU0="44" MHz0="720" FPC0="128" />
   </P>
   <ID kG0="1" kG1="1" kG2="1" b0="2" b1="2" ppdO="0" ppdLS="0" ppdAll="0" >
    <K i="0" wG0="16" wG1="16" mT0="2" mT1="2" b0="2" b1="2" nlpaA="1" lspaA="8" tspaA="8" nlpeA="1" lspeA="32" tspeA="32" nlpaB="1" lspaB="32" tspaB="32" nlpeB="1" lspeB="8" tspeB="8" u0="8" u1="1" />
   </ID>
  </S>
  <B t="0.110489" u="ms" />
 </TE>
 <TE>
  <S>
   <P>
    <TC t="0" n="3" st0="2" sz0="1071" st1="4284" sz1="1071" st2="9176328" sz2="2" />
    <TA t="0" n="3" st0="2" sz0="1071" st1="4284" sz1="1071" st2="9176328" sz2="2" />
    <TB t="0" n="3" st0="2" sz0="1071" st1="4284" sz1="1071" st2="9176328" sz2="2" />
    <O t="0" a="0" b="0" o="1" nF="2" nB="1" nS="1" >
     <IA n="3" i0="3" i1="0" i2="2" />
     <IB n="3" i0="1" i1="3" i2="2" />
    </O>
    <DP n="1" d0="Hawaii" CU0="44" MHz0="720" FPC0="128" />
   </P>
   <ID kG0="1" kG1="1" kG2="1" b0="2" b1="2" ppdO="0" ppdLS="0" ppdAll="0" >
    <K i="0" wG0="16" wG1="16" mT0="4" mT1="4" b0="2" b1="2" nlpaA="1" lspaA="4" tspaA="4" nlpeA="1" lspeA="64" tspeA="64" nlpaB="1" lspaB="64" tspaB="64" nlpeB="1" lspeB="4" tspeB="4" u0="4" u1="1" />
   </ID>
  </S>
  <B t="2.552489" u="ms" />
 </TE>
 <TE>
  <S>
   <P>
    <TC t="0" n="3" st0="2" sz0="1072" st1="4288" sz1="1072" st2="9193472" sz2="2" />
    <TA t="0" n="3" st0="2" sz0="1071" st1="4284" sz1="1072" st2="9184896" sz2="2" />
    <TB t="0" n="3" st0="2" sz0="1072" st1="4288" sz1="1071" st2="9184896" sz2="2" />
    <O t="0" a="0" b="0" o="1" nF="2" nB="1" nS="1" >
     <IA n="3" i0="3" i1="0" i2="2" />
     <IB n="3" i0="1" i1="3" i2="2" />
    </O>
    <DP n="1" d0="Hawaii" CU0="44" MHz0="720" FPC0="128" />
   </P>
   <ID kG0="1" kG1="1" kG2="1" b0="2" b1="2" ppdO="0" ppdLS="0" ppdAll="0" >
    <K i="0" wG0="16" wG1="16" mT0="5" mT1="5" b0="2" b1="2" nlpaA="1" lspaA="16" tspaA="16" nlpeA="5" lspeA="16" tspeA="80" nlpaB="5" lspaB="16" tspaB="80" nlpeB="1" lspeB="16" tspeB="16" u0="16" u1="1" />
   </ID>
  </S>
  <B t="3.010089" u="ms" />
 </TE>
 <TE>
  <S>
   <P>
    <TC t="0" n="3" st0="2" sz0="16" st1="64" sz1="16" st2="2048" sz2="2" />
    <TA t="0" n="3" st0="2" sz0="15" st1="60" sz1="16" st2="1920" sz2="2" />
    <TB t="0" n="3" st0="2" sz0="16" st1="64" sz1="15" st2="1920" sz2="2" />
    <O t="0" a="0" b="0" o="1" nF="2" nB="1" nS="1" >
     <IA n="3" i0="3" i1="0" i2="2" />
     <IB n="3" i0="1" i1="3" i2="2" />
    </O>
    <DP n="1" d0="Hawaii" CU0="44" MHz0="720" FPC0="128" />
   </P>
   <ID kG0="1" kG1="1" kG2="1" b0="2" b1="2" ppdO="0" ppdLS="0" ppdAll="0" >
    <K i="0" wG0="16" wG1="16" mT0="2" mT1="2" b0="2" b1="2" nlpaA="1" lspaA="8" tspaA="8" nlpeA="1" lspeA="32" tspeA="32" nlpaB="1" lspaB="32" tspaB="32" nlpeB="1" lspeB="8" tspeB="8" u0="8" u1="1" />
   </ID>
  </S>
  <B t="0.111956" u="ms" />
 </TE>
 <TE>
  <S>
   <P>
    <TC t="0" n="3" st0="2" sz0="464" st1="1856" sz1="464" st2="1722368" sz2="2" />
    <TA t="0" n="3" st0="2" sz0="463" st1="1852" sz1="464" st2="1718656" sz2="2" />
    <TB t="0" n="3" st0="2" sz0="464" st1="1856" sz1="463" st2="1718656" sz2="2" />
    <O t="0" a="0" b="0" o="1" nF="2" nB="1" nS="1" >
     <IA n="3" i0="3" i1="0" i2="2" />
     <IB n="3" i0="1" i1="3" i2="2" />
    </O>
    <DP n="1" d0="Hawaii" CU0="44" MHz0="720" FPC0="128" />
   </P>
   <ID kG0="1" kG1="1" kG2="1" b0="2" b1="2" ppdO="0" ppdLS="0" ppdAll="0" >
    <K i="0" wG0="16" wG1="16" mT0="4" mT1="4" b0="2" b1="2" nlpaA="1" lspaA="8" tspaA="8" nlpeA="2" lspeA="32" tspeA="64" nlpaB="2" lspaB="32" tspaB="64" nlpeB="1" lspeB="8" tspeB="8" u0="8" u1="1" />
   </ID>
  </S>
  <B t="0.390133" u="ms" />
 </TE>
 <TE>
  <S>
   <P>
    <TC t="0" n="3" st0="2" sz0="176" st1="704" sz1="176" st2="247808" sz2="2" />
    <TA t="0" n="3" st0="2" sz0="175" st1="700" sz1="176" st2="246400" sz2="2" />
    <TB t="0" n="3" st0="2" sz0="176" st1="704" sz1="175" st2="246400" sz2="2" />
    <O t="0" a="0" b="0" o="1" nF="2" nB="1" nS="1" >
     <IA n="3" i0="3" i1="0" i2="2" />
     <IB n="3" i0="1" i1="3" i2="2" />
    </O>
    <DP n="1" d0="Hawaii" CU0="44" MHz0="720" FPC0="128" />
   </P>
   <ID kG0="1" kG1="1" kG2="1" b0="2" b1="2" ppdO="0" ppdLS="0" ppdAll="0" >
    <K i="0" wG0="16" wG1="16" mT0="2" mT1="2" b0="2" b1="2" nlpaA="1" lspaA="8" tspaA="8" nlpeA="1" lspeA="32" tspeA="32" nlpaB="1" lspaB="32" tspaB="32" nlpeB="1" lspeB="8" tspeB="8" u0="8" u1="1" />
   </ID>
  </S>
  <B t="0.156933" u="ms" />
 </TE>
 <TE>
  <S>
   <P>
    <TC t="0" n="3" st0="2" sz0="176" st1="704" sz1="176" st2="247808" sz2="2" />
    <TA t="0" n="3" st0="2" sz0="176" st1="704" sz1="176" st2="247808" sz2="2" />
    <TB t="0" n="3" st0="2" sz0="176" st1="704" sz1="176" st2="247808" sz2="2" />
    <O t="0" a="0" b="0" o="1" nF="2" nB="1" nS="1" >
     <IA n="3" i0="3" i1="0" i2="2" />
     <IB n="3" i0="1" i1="3" i2="2" />
    </O>
    <DP n="1" d0="Hawaii" CU0="44" MHz0="720" FPC0="128" />
   </P>
   <ID kG0="2" kG1="2" kG2="1" b0="1" b1="1" ppdO="0" ppdLS="0" ppdAll="0" >
    <K i="0" wG0="8" wG1="8" mT0="2" mT1="2" b0="0" b1="0" nlpaA="1" lspaA="16" tspaA="16" nlpeA="4" lspeA="4" tspeA="16" nlpaB="4" lspaB="4" tspaB="16" nlpeB="1" lspeB="16" tspeB="16" u0="16" u1="0" />
    <K i="1" wG0="8" wG1="8" mT0="2" mT1="2" b0="1" b1="0" nlpaA="1" lspaA="16" tspaA="16" nlpeA="4" lspeA="4" tspeA="16" nlpaB="4" lspaB="4" tspaB="16" nlpeB="1" lspeB="16" tspeB="16" u0="16" u1="0" />
    <K i="2" wG0="8" wG1="8" mT0="2" mT1="2" b0="0" b1="1" nlpaA="1" lspaA="16" tspaA="16" nlpeA="4" lspeA="4" tspeA="16" nlpaB="4" lspaB="4" tspaB="16" nlpeB="1" lspeB="16" tspeB="16" u0="16" u1="0" />
    <K i="3" wG0="8" wG1="8" mT0="2" mT1="2" b0="1" b1="1" nlpaA="1" lspaA="16" tspaA="16" nlpeA="4" lspeA="4" tspeA="16" nlpaB="4" lspaB="4" tspaB="16" nlpeB="1" lspeB="16" tspeB="16" u0="16" u1="0" />
   </ID>
  </S>
  <B t="0.153511" u="ms" />
 </TE>
 <TE>
  <S>
   <P>
    <TC t="0" n="3" st0="2" sz0="2192" st1="8768" sz1="2192" st2="38438912" sz2="2" />
    <TA t="0" n="3" st0="2" sz0="2191" st1="8764" sz1="2192" st2="38421376" sz2="2" />
    <TB t="0" n="3" st0="2" sz0="2192" st1="8768" sz1="2191" st2="38421376" sz2="2" />
    <O t="0" a="0" b="0" o="1" nF="2" nB="1" nS="1" >
     <IA n="3" i0="3" i1="0" i2="2" />
     <IB n="3" i0="1" i1="3" i2="2" />
    </O>
    <DP n="1" d0="Hawaii" CU0="44" MHz0="720" FPC0="128" />
   </P>
   <ID kG0="2" kG1="2" kG2="1" b0="1" b1="1" ppdO="0" ppdLS="0" ppdAll="0" >
    <K i="0" wG0="16" wG1="16" mT0="4" mT1="4" b0="0" b1="0" nlpaA="1" lspaA="16" tspaA="16" nlpeA="4" lspeA="16" tspeA="64" nlpaB="4" lspaB="16" tspaB="64" nlpeB="1" lspeB="16" tspeB="16" u0="16" u1="1" />
    <K i="1" wG0="16" wG1="16" mT0="4" mT1="4" b0="1" b1="0" nlpaA="1" lspaA="16" tspaA="16" nlpeA="4" lspeA="16" tspeA="64" nlpaB="4" lspaB="16" tspaB="64" nlpeB="1" lspeB="16" tspeB="16" u0="16" u1="1" />
    <K i="2" wG0="16" wG1="16" mT0="4" mT1="4" b0="0" b1="1" nlpaA="1" lspaA="16" tspaA="16" nlpeA="4" lspeA="16" tspeA="64" nlpaB="4" lspaB="16" tspaB="64" nlpeB="1" lspeB="16" tspeB="16" u0="16" u1="1" />
    <K i="3" wG0="16" wG1="16" mT0="4" mT1="4" b0="1" b1="1" nlpaA="1" lspaA="16" tspaA="16" nlpeA="4" lspeA="16" tspeA="64" nlpaB="4" lspaB="16" tspaB="64" nlpeB="1" lspeB="16" tspeB="16" u0="16" u1="1" />
   </ID>
  </S>
  <B t="17.625913" u="ms" />
 </TE>
 <TE>
  <S>
   <P>
    <TC t="0" n="3" st0="2" sz0="31" st1="124" sz1="31" st2="7688" sz2="2" />
    <TA t="0" n="3" st0="2" sz0="32" st1="128" sz1="31" st2="7936" sz2="2" />
    <TB t="0" n="3" st0="2" sz0="31" st1="124" sz1="32" st2="7936" sz2="2" />
    <O t="0" a="0" b="0" o="1" nF="2" nB="1" nS="1" >
     <IA n="3" i0="3" i1="0" i2="2" />
     <IB n="3" i0="1" i1="3" i2="2" />
    </O>
    <DP n="1" d0="Hawaii" CU0="44" MHz0="720" FPC0="128" />
   </P>
   <ID kG0="1" kG1="1" kG2="1" b0="2" b1="2" ppdO="0" ppdLS="0" ppdAll="0" >
    <K i="0" wG0="16" wG1="16" mT0="3" mT1="3" b0="2" b1="2" nlpaA="1" lspaA="4" tspaA="4" nlpeA="1" lspeA="48" tspeA="48" nlpaB="1" lspaB="48" tspaB="48" nlpeB="1" lspeB="4" tspeB="4" u0="4" u1="0" />
   </ID>
  </S>
  <B t="0.133956" u="ms" />
 </TE>
 <TE>
  <S>
   <P>
    <TC t="0" n="3" st0="2" sz0="256" st1="1024" sz1="256" st2="524288" sz2="2" />
    <TA t="0" n="3" st0="2" sz0="255" st1="1020" sz1="256" st2="522240" sz2="2" />
    <TB t="0" n="3" st0="2" sz0="256" st1="1024" sz1="255" st2="522240" sz2="2" />
    <O t="0" a="0" b="0" o="1" nF="2" nB="1" nS="1" >
     <IA n="3" i0="3" i1="0" i2="2" />
     <IB n="3" i0="1" i1="3" i2="2" />
    </O>
    <DP n="1" d0="Hawaii" CU0="44" MHz0="720" FPC0="128" />
   </P>
   <ID kG0="1" kG1="1" kG2="1" b0="2" b1="2" ppdO="0" ppdLS="0" ppdAll="0" >
    <K i="0" wG0="16" wG1="16" mT0="3" mT1="3" b0="2" b1="2" nlpaA="1" lspaA="4" tspaA="4" nlpeA="1" lspeA="48" tspeA="48" nlpaB="1" lspaB="48" tspaB="48" nlpeB="1" lspeB="4" tspeB="4" u0="4" u1="1" />
   </ID>
  </S>
  <B t="0.259600" u="ms" />
 </TE>
 <TE>
  <S>
   <P>
    <TC t="0" n="3" st0="2" sz0="31" st1="124" sz1="31" st2="7688" sz2="2" />
    <TA t="0" n="3" st0="2" sz0="32" st1="128" sz1="31" st2="7936" sz2="2" />
    <TB t="0" n="3" st0="2" sz0="31" st1="124" sz1="32" st2="7936" sz2="2" />
    <O t="0" a="0" b="0" o="1" nF="2" nB="1" nS="1" >
     <IA n="3" i0="3" i1="0" i2="2" />
     <IB n="3" i0="1" i1="3" i2="2" />
    </O>
    <DP n="1" d0="Hawaii" CU0="44" MHz0="720" FPC0="128" />
   </P>
   <ID kG0="1" kG1="1" kG2="1" b0="2" b1="2" ppdO="0" ppdLS="0" ppdAll="0" >
    <K i="0" wG0="8" wG1="8" mT0="2" mT1="2" b0="2" b1="2" nlpaA="1" lspaA="4" tspaA="4" nlpeA="1" lspeA="16" tspeA="16" nlpaB="1" lspaB="16" tspaB="16" nlpeB="1" lspeB="4" tspeB="4" u0="4" u1="0" />
   </ID>
  </S>
  <B t="0.137867" u="ms" />
 </TE>
 <TE>
  <S>
   <P>
    <TC t="0" n="3" st0="2" sz0="256" st1="1024" sz1="256" st2="524288" sz2="2" />
    <TA t="0" n="3" st0="2" sz0="255" st1="1020" sz1="256" st2="522240" sz2="2" />
    <TB t="0" n="3" st0="2" sz0="256" st1="1024" sz1="255" st2="522240" sz2="2" />
    <O t="0" a="0" b="0" o="1" nF="2" nB="1" nS="1" >
     <IA n="3" i0="3" i1="0" i2="2" />
     <IB n="3" i0="1" i1="3" i2="2" />
    </O>
    <DP n="1" d0="Hawaii" CU0="44" MHz0="720" FPC0="128" />
   </P>
   <ID kG0="2" kG1="2" kG2="1" b0="1" b1="1" ppdO="0" ppdLS="0" ppdAll="0" >
    <K i="0" wG0="16" wG1="16" mT0="2" mT1="2" b0="0" b1="0" nlpaA="1" lspaA="4" tspaA="4" nlpeA="1" lspeA="32" tspeA="32" nlpaB="1" lspaB="32" tspaB="32" nlpeB="1" lspeB="4" tspeB="4" u0="4" u1="1" />
    <K i="1" wG0="16" wG1="16" mT0="2" mT1="2" b0="1" b1="0" nlpaA="1" lspaA="4" tspaA="4" nlpeA="1" lspeA="32" tspeA="32" nlpaB="1" lspaB="32" tspaB="32" nlpeB="1" lspeB="4" tspeB="4" u0="4" u1="1" />
    <K i="2" wG0="16" wG1="16" mT0="2" mT1="2" b0="0" b1="1" nlpaA="1" lspaA="4" tspaA="4" nlpeA="1" lspeA="32" tspeA="32" nlpaB="1" lspaB="32" tspaB="32" nlpeB="1" lspeB="4" tspeB="4" u0="4" u1="1" />
    <K i="3" wG0="16" wG1="16" mT0="2" mT1="2" b0="1" b1="1" nlpaA="1" lspaA="4" tspaA="4" nlpeA="1" lspeA="32" tspeA="32" nlpaB="1" lspaB="32" tspaB="32" nlpeB="1" lspeB="4" tspeB="4" u0="4" u1="1" />
   </ID>
  </S>
  <B t="0.224889" u="ms" />
 </TE>
 <TE>
  <S>
   <P>
    <TC t="0" n="3" st0="2" sz0="736" st1="2944" sz1="736" st2="4333568" sz2="2" />
    <TA t="0" n="3" st0="2" sz0="735" st1="2940" sz1="736" st2="4327680" sz2="2" />
    <TB t="0" n="3" st0="2" sz0="736" st1="2944" sz1="735" st2="4327680" sz2="2" />
    <O t="0" a="0" b="0" o="1" nF="2" nB="1" nS="1" >
     <IA n="3" i0="3" i1="0" i2="2" />
     <IB n="3" i0="1" i1="3" i2="2" />
    </O>
    <DP n="1" d0="Hawaii" CU0="44" MHz0="720" FPC0="128" />
   </P>
   <ID kG0="2" kG1="2" kG2="1" b0="1" b1="1" ppdO="0" ppdLS="0" ppdAll="0" >
    <K i="0" wG0="8" wG1="8" mT0="4" mT1="4" b0="0" b1="0" nlpaA="1" lspaA="8" tspaA="8" nlpeA="4" lspeA="8" tspeA="32" nlpaB="4" lspaB="8" tspaB="32" nlpeB="1" lspeB="8" tspeB="8" u0="8" u1="1" />
    <K i="1" wG0="8" wG1="8" mT0="4" mT1="4" b0="1" b1="0" nlpaA="1" lspaA="8" tspaA="8" nlpeA="4" lspeA="8" tspeA="32" nlpaB="4" lspaB="8" tspaB="32" nlpeB="1" lspeB="8" tspeB="8" u0="8" u1="1" />
    <K i="2" wG0="8" wG1="8" mT0="4" mT1="4" b0="0" b1="1" nlpaA="1" lspaA="8" tspaA="8" nlpeA="4" lspeA="8" tspeA="32" nlpaB="4" lspaB="8" tspaB="32" nlpeB="1" lspeB="8" tspeB="8" u0="8" u1="1" />
    <K i="3" wG0="8" wG1="8" mT0="4" mT1="4" b0="1" b1="1" nlpaA="1" lspaA="8" tspaA="8" nlpeA="4" lspeA="8" tspeA="32" nlpaB="4" lspaB="8" tspaB="32" nlpeB="1" lspeB="8" tspeB="8" u0="8" u1="1" />
   </ID>
  </S>
  <B t="1.016400" u="ms" />
 </TE>
 <TE>
  <S>
   <P>
    <TC t="0" n="3" st0="2" sz0="16" st1="64" sz1="16" st2="2048" sz2="2" />
    <TA t="0" n="3" st0="2" sz0="16" st1="64" sz1="16" st2="2048" sz2="2" />
    <TB t="0" n="3" st0="2" sz0="16" st1="64" sz1="16" st2="2048" sz2="2" />
    <O t="0" a="0" b="0" o="1" nF="2" nB="1" nS="1" >
     <IA n="3" i0="3" i1="0" i2="2" />
     <IB n="3" i0="1" i1="3" i2="2" />
    </O>
    <DP n="1" d0="Hawaii" CU0="44" MHz0="720" FPC0="128" />
   </P>
   <ID kG0="2" kG1="2" kG2="1" b0="1" b1="1" ppdO="0" ppdLS="0" ppdAll="0" >
    <K i="0" wG0="8" wG1="8" mT0="2" mT1="2" b0="0" b1="0" nlpaA="1" lspaA="4" tspaA="4" nlpeA="1" lspeA="16" tspeA="16" nlpaB="1" lspaB="16" tspaB="16" nlpeB="1" lspeB="4" tspeB="4" u0="4" u1="0" />
    <K i="1" wG0="8" wG1="8" mT0="2" mT1="2" b0="1" b1="0" nlpaA="1" lspaA="4" tspaA="4" nlpeA="1" lspeA="16" tspeA="16" nlpaB="1" lspaB="16" tspaB="16" nlpeB="1" lspeB="4" tspeB="4" u0="4" u1="0" />
    <K i="2" wG0="8" wG1="8" mT0="2" mT1="2" b0="0" b1="1" nlpaA="1" lspaA="4" tspaA="4" nlpeA="1" lspeA="16" tspeA="16" nlpaB="1" lspaB="16" tspaB="16" nlpeB="1" lspeB="4" tspeB="4" u0="4" u1="0" />
    <K i="3" wG0="8" wG1="8" mT0="2" mT1="2" b0="1" b1="1" nlpaA="1" lspaA="4" tspaA="4" nlpeA="1" lspeA="16" tspeA="16" nlpaB="1" lspaB="16" tspaB="16" nlpeB="1" lspeB="4" tspeB="4" u0="4" u1="0" />
   </ID>
  </S>
  <B t="0.113911" u="ms" />
 </TE>
 <TE>
  <S>
   <P>
    <TC t="0" n="3" st0="2" sz0="255" st1="1020" sz1="255" st2="520200" sz2="2" />
    <TA t="0" n="3" st0="2" sz0="255" st1="1020" sz1="255" st2="520200" sz2="2" />
    <TB t="0" n="3" st0="2" sz0="255" st1="1020" sz1="255" st2="520200" sz2="2" />
    <O t="0" a="0" b="0" o="1" nF="2" nB="1" nS="1" >
     <IA n="3" i0="3" i1="0" i2="2" />
     <IB n="3" i0="1" i1="3" i2="2" />
    </O>
    <DP n="1" d0="Hawaii" CU0="44" MHz0="720" FPC0="128" />
   </P>
   <ID kG0="1" kG1="1" kG2="1" b0="2" b1="2" ppdO="0" ppdLS="0" ppdAll="0" >
    <K i="0" wG0="8" wG1="8" mT0="2" mT1="2" b0="2" b1="2" nlpaA="1" lspaA="4" tspaA="4" nlpeA="1" lspeA="16" tspeA="16" nlpaB="1" lspaB="16" tspaB="16" nlpeB="1" lspeB="4" tspeB="4" u0="4" u1="1" />
   </ID>
  </S>
  <B t="0.233689" u="ms" />
 </TE>
 <TE>
  <S>
   <P>
    <TC t="0" n="3" st0="2" sz0="1264" st1="5056" sz1="1264" st2="12781568" sz2="2" />
    <TA t="0" n="3" st0="2" sz0="1264" st1="5056" sz1="1264" st2="12781568" sz2="2" />
    <TB t="0" n="3" st0="2" sz0="1264" st1="5056" sz1="1264" st2="12781568" sz2="2" />
    <O t="0" a="0" b="0" o="1" nF="2" nB="1" nS="1" >
     <IA n="3" i0="3" i1="0" i2="2" />
     <IB n="3" i0="1" i1="3" i2="2" />
    </O>
    <DP n="1" d0="Hawaii" CU0="44" MHz0="720" FPC0="128" />
   </P>
   <ID kG0="1" kG1="1" kG2="1" b0="2" b1="2" ppdO="0" ppdLS="0" ppdAll="0" >
    <K i="0" wG0="16" wG1="16" mT0="5" mT1="5" b0="2" b1="2" nlpaA="1" lspaA="16" tspaA="16" nlpeA="5" lspeA="16" tspeA="80" nlpaB="5" lspaB="16" tspaB="80" nlpeB="1" lspeB="16" tspeB="16" u0="16" u1="0" />
   </ID>
  </S>
  <B t="3.646623" u="ms" />
 </TE>
 <TE>
  <S>
   <P>
    <TC t="0" n="3" st0="2" sz0="1472" st1="5888" sz1="1472" st2="17334272" sz2="2" />
    <TA t="0" n="3" st0="2" sz0="1472" st1="5888" sz1="1472" st2="17334272" sz2="2" />
    <TB t="0" n="3" st0="2" sz0="1472" st1="5888" sz1="1472" st2="17334272" sz2="2" />
    <O t="0" a="0" b="0" o="1" nF="2" nB="1" nS="1" >
     <IA n="3" i0="3" i1="0" i2="2" />
     <IB n="3" i0="1" i1="3" i2="2" />
    </O>
    <DP n="1" d0="Hawaii" CU0="44" MHz0="720" FPC0="128" />
   </P>
   <ID kG0="1" kG1="1" kG2="1" b0="2" b1="2" ppdO="0" ppdLS="0" ppdAll="0" >
    <K i="0" wG0="16" wG1="16" mT0="6" mT1="6" b0="2" b1="2" nlpaA="1" lspaA="8" tspaA="8" nlpeA="3" lspeA="32" tspeA="96" nlpaB="3" lspaB="32" tspaB="96" nlpeB="1" lspeB="8" tspeB="8" u0="8" u1="0" />
   </ID>
  </S>
  <B t="5.933156" u="ms" />
 </TE>
 <TE>
  <S>
   <P>
    <TC t="0" n="3" st0="2" sz0="736" st1="2944" sz1="736" st2="4333568" sz2="2" />
    <TA t="0" n="3" st0="2" sz0="735" st1="2940" sz1="736" st2="4327680" sz2="2" />
    <TB t="0" n="3" st0="2" sz0="736" st1="2944" sz1="735" st2="4327680" sz2="2" />
    <O t="0" a="0" b="0" o="1" nF="2" nB="1" nS="1" >
     <IA n="3" i0="3" i1="0" i2="2" />
     <IB n="3" i0="1" i1="3" i2="2" />
    </O>
    <DP n="1" d0="Hawaii" CU0="44" MHz0="720" FPC0="128" />
   </P>
   <ID kG0="1" kG1="1" kG2="1" b0="2" b1="2" ppdO="0" ppdLS="0" ppdAll="0" >
    <K i="0" wG0="16" wG1="16" mT0="8" mT1="8" b0="2" b1="2" nlpaA="1" lspaA="8" tspaA="8" nlpeA="4" lspeA="32" tspeA="128" nlpaB="4" lspaB="32" tspaB="128" nlpeB="1" lspeB="8" tspeB="8" u0="8" u1="1" />
   </ID>
  </S>
  <B t="1.078978" u="ms" />
 </TE>
 <TE>
  <S>
   <P>
    <TC t="0" n="3" st0="2" sz0="175" st1="700" sz1="175" st2="245000" sz2="2" />
    <TA t="0" n="3" st0="2" sz0="175" st1="700" sz1="175" st2="245000" sz2="2" />
    <TB t="0" n="3" st0="2" sz0="175" st1="700" sz1="175" st2="245000" sz2="2" />
    <O t="0" a="0" b="0" o="1" nF="2" nB="1" nS="1" >
     <IA n="3" i0="3" i1="0" i2="2" />
     <IB n="3" i0="1" i1="3" i2="2" />
    </O>
    <DP n="1" d0="Hawaii" CU0="44" MHz0="720" FPC0="128" />
   </P>
   <ID kG0="1" kG1="1" kG2="1" b0="2" b1="2" ppdO="0" ppdLS="0" ppdAll="0" >
    <K i="0" wG0="16" wG1="16" mT0="2" mT1="2" b0="2" b1="2" nlpaA="1" lspaA="8" tspaA="8" nlpeA="1" lspeA="32" tspeA="32" nlpaB="1" lspaB="32" tspaB="32" nlpeB="1" lspeB="8" tspeB="8" u0="8" u1="1" />
   </ID>
  </S>
  <B t="0.173556" u="ms" />
 </TE>
 <TE>
  <S>
   <P>
    <TC t="0" n="3" st0="2" sz0="896" st1="3584" sz1="896" st2="6422528" sz2="2" />
    <TA t="0" n="3" st0="2" sz0="896" st1="3584" sz1="896" st2="6422528" sz2="2" />
    <TB t="0" n="3" st0="2" sz0="896" st1="3584" sz1="896" st2="6422528" sz2="2" />
    <O t="0" a="0" b="0" o="1" nF="2" nB="1" nS="1" >
     <IA n="3" i0="3" i1="0" i2="2" />
     <IB n="3" i0="1" i1="3" i2="2" />
    </O>
    <DP n="1" d0="Hawaii" CU0="44" MHz0="720" FPC0="128" />
   </P>
   <ID kG0="1" kG1="1" kG2="1" b0="2" b1="2" ppdO="0" ppdLS="0" ppdAll="0" >
    <K i="0" wG0="16" wG1="16" mT0="6" mT1="6" b0="2" b1="2" nlpaA="1" lspaA="8" tspaA="8" nlpeA="3" lspeA="32" tspeA="96" nlpaB="3" lspaB="32" tspaB="96" nlpeB="1" lspeB="8" tspeB="8" u0="8" u1="0" />
   </ID>
  </S>
  <B t="1.897867" u="ms" />
 </TE>
 <TE>
  <S>
   <P>
    <TC t="0" n="3" st0="2" sz0="2192" st1="8768" sz1="2192" st2="38438912" sz2="2" />
    <TA t="0" n="3" st0="2" sz0="2191" st1="8764" sz1="2192" st2="38421376" sz2="2" />
    <TB t="0" n="3" st0="2" sz0="2192" st1="8768" sz1="2191" st2="38421376" sz2="2" />
    <O t="0" a="0" b="0" o="1" nF="2" nB="1" nS="1" >
     <IA n="3" i0="3" i1="0" i2="2" />
     <IB n="3" i0="1" i1="3" i2="2" />
    </O>
    <DP n="1" d0="Hawaii" CU0="44" MHz0="720" FPC0="128" />
   </P>
   <ID kG0="2" kG1="2" kG2="1" b0="1" b1="1" ppdO="0" ppdLS="0" ppdAll="0" >
    <K i="0" wG0="16" wG1="16" mT0="5" mT1="5" b0="0" b1="0" nlpaA="1" lspaA="16" tspaA="16" nlpeA="5" lspeA="16" tspeA="80" nlpaB="5" lspaB="16" tspaB="80" nlpeB="1" lspeB="16" tspeB="16" u0="16" u1="1" />
    <K i="1" wG0="16" wG1="16" mT0="5" mT1="5" b0="1" b1="0" nlpaA="1" lspaA="16" tspaA="16" nlpeA="5" lspeA="16" tspeA="80" nlpaB="5" lspaB="16" tspaB="80" nlpeB="1" lspeB="16" tspeB="16" u0="16" u1="1" />
    <K i="2" wG0="16" wG1="16" mT0="5" mT1="5" b0="0" b1="1" nlpaA="1" lspaA="16" tspaA="16" nlpeA="5" lspeA="16" tspeA="80" nlpaB="5" lspaB="16" tspaB="80" nlpeB="1" lspeB="16" tspeB="16" u0="16" u1="1" />
    <K i="3" wG0="16" wG1="16" mT0="5" mT1="5" b0="1" b1="1" nlpaA="1" lspaA="16" tspaA="16" nlpeA="5" lspeA="16" tspeA="80" nlpaB="5" lspaB="16" tspaB="80" nlpeB="1" lspeB="16" tspeB="16" u0="16" u1="1" />
   </ID>
  </S>
  <B t="18.153425" u="ms" />
 </TE>
 <TE>
  <S>
   <P>
    <TC t="0" n="3" st0="2" sz0="63" st1="252" sz1="63" st2="31752" sz2="2" />
    <TA t="0" n="3" st0="2" sz0="63" st1="252" sz1="63" st2="31752" sz2="2" />
    <TB t="0" n="3" st0="2" sz0="63" st1="252" sz1="63" st2="31752" sz2="2" />
    <O t="0" a="0" b="0" o="1" nF="2" nB="1" nS="1" >
     <IA n="3" i0="3" i1="0" i2="2" />
     <IB n="3" i0="1" i1="3" i2="2" />
    </O>
    <DP n="1" d0="Hawaii" CU0="44" MHz0="720" FPC0="128" />
   </P>
   <ID kG0="1" kG1="1" kG2="1" b0="2" b1="2" ppdO="0" ppdLS="0" ppdAll="0" >
    <K i="0" wG0="16" wG1="16" mT0="2" mT1="2" b0="2" b1="2" nlpaA="1" lspaA="8" tspaA="8" nlpeA="1" lspeA="32" tspeA="32" nlpaB="1" lspaB="32" tspaB="32" nlpeB="1" lspeB="8" tspeB="8" u0="8" u1="1" />
   </ID>
  </S>
  <B t="0.144711" u="ms" />
 </TE>
 <TE>
  <S>
   <P>
    <TC t="0" n="3" st0="2" sz0="2464" st1="9856" sz1="2464" st2="48570368" sz2="2" />
    <TA t="0" n="3" st0="2" sz0="2463" st1="9852" sz1="2464" st2="48550656" sz2="2" />
    <TB t="0" n="3" st0="2" sz0="2464" st1="9856" sz1="2463" st2="48550656" sz2="2" />
    <O t="0" a="0" b="0" o="1" nF="2" nB="1" nS="1" >
     <IA n="3" i0="3" i1="0" i2="2" />
     <IB n="3" i0="1" i1="3" i2="2" />
    </O>
    <DP n="1" d0="Hawaii" CU0="44" MHz0="720" FPC0="128" />
   </P>
   <ID kG0="2" kG1="2" kG2="1" b0="1" b1="1" ppdO="0" ppdLS="0" ppdAll="0" >
    <K i="0" wG0="16" wG1="16" mT0="7" mT1="7" b0="0" b1="0" nlpaA="1" lspaA="16" tspaA="16" nlpeA="7" lspeA="16" tspeA="112" nlpaB="7" lspaB="16" tspaB="112" nlpeB="1" lspeB="16" tspeB="16" u0="16" u1="1" />
    <K i="1" wG0="16" wG1="16" mT0="7" mT1="7" b0="1" b1="0" nlpaA="1" lspaA="16" tspaA="16" nlpeA="7" lspeA="16" tspeA="112" nlpaB="7" lspaB="16" tspaB="112" nlpeB="1" lspeB="16" tspeB="16" u0="16" u1="1" />
    <K i="2" wG0="16" wG1="16" mT0="7" mT1="7" b0="0" b1="1" nlpaA="1" lspaA="16" tspaA="16" nlpeA="7" lspeA="16" tspeA="112" nlpaB="7" lspaB="16" tspaB="112" nlpeB="1" lspeB="16" tspeB="16" u0="16" u1="1" />
    <K i="3" wG0="16" wG1="16" mT0="7" mT1="7" b0="1" b1="1" nlpaA="1" lspaA="16" tspaA="16" nlpeA="7" lspeA="16" tspeA="112" nlpaB="7" lspaB="16" tspaB="112" nlpeB="1" lspeB="16" tspeB="16" u0="16" u1="1" />
   </ID>
  </S>
  <B t="19.211380" u="ms" />
 </TE>
 <TE>
  <S>
   <P>
    <TC t="0" n="3" st0="2" sz0="2191" st1="8764" sz1="2191" st2="38403848" sz2="2" />
    <TA t="0" n="3" st0="2" sz0="2191" st1="8764" sz1="2191" st2="38403848" sz2="2" />
    <TB t="0" n="3" st0="2" sz0="2191" st1="8764" sz1="2191" st2="38403848" sz2="2" />
    <O t="0" a="0" b="0" o="1" nF="2" nB="1" nS="1" >
     <IA n="3" i0="3" i1="0" i2="2" />
     <IB n="3" i0="1" i1="3" i2="2" />
    </O>
    <DP n="1" d0="Hawaii" CU0="44" MHz0="720" FPC0="128" />
   </P>
   <ID kG0="2" kG1="2" kG2="1" b0="1" b1="1" ppdO="0" ppdLS="0" ppdAll="0" >
    <K i="0" wG0="16" wG1="16" mT0="4" mT1="4" b0="0" b1="0" nlpaA="1" lspaA="16" tspaA="16" nlpeA="4" lspeA="16" tspeA="64" nlpaB="4" lspaB="16" tspaB="64" nlpeB="1" lspeB="16" tspeB="16" u0="16" u1="1" />
    <K i="1" wG0="16" wG1="16" mT0="4" mT1="4" b0="1" b1="0" nlpaA="1" lspaA="16" tspaA="16" nlpeA="4" lspeA="16" tspeA="64" nlpaB="4" lspaB="16" tspaB="64" nlpeB="1" lspeB="16" tspeB="16" u0="16" u1="1" />
    <K i="2" wG0="16" wG1="16" mT0="4" mT1="4" b0="0" b1="1" nlpaA="1" lspaA="16" tspaA="16" nlpeA="4" lspeA="16" tspeA="64" nlpaB="4" lspaB="16" tspaB="64" nlpeB="1" lspeB="16" tspeB="16" u0="16" u1="1" />
    <K i="3" wG0="16" wG1="16" mT0="4" mT1="4" b0="1" b1="1" nlpaA="1" lspaA="16" tspaA="16" nlpeA="4" lspeA="16" tspeA="64" nlpaB="4" lspaB="16" tspaB="64" nlpeB="1" lspeB="16" tspeB="16" u0="16" u1="1" />
   </ID>
  </S>
  <B t="17.042180" u="ms" />
 </TE>
 <TE>
  <S>
   <P>
    <TC t="0" n="3" st0="2" sz0="1472" st1="5888" sz1="1472" st2="17334272" sz2="2" />
    <TA t="0" n="3" st0="2" sz0="1472" st1="5888" sz1="1472" st2="17334272" sz2="2" />
    <TB t="0" n="3" st0="2" sz0="1472" st1="5888" sz1="1472" st2="17334272" sz2="2" />
    <O t="0" a="0" b="0" o="1" nF="2" nB="1" nS="1" >
     <IA n="3" i0="3" i1="0" i2="2" />
     <IB n="3" i0="1" i1="3" i2="2" />
    </O>
    <DP n="1" d0="Hawaii" CU0="44" MHz0="720" FPC0="128" />
   </P>
   <ID kG0="1" kG1="1" kG2="1" b0="2" b1="2" ppdO="0" ppdLS="0" ppdAll="0" >
    <K i="0" wG0="16" wG1="16" mT0="5" mT1="5" b0="2" b1="2" nlpaA="1" lspaA="16" tspaA="16" nlpeA="5" lspeA="16" tspeA="80" nlpaB="5" lspaB="16" tspaB="80" nlpeB="1" lspeB="16" tspeB="16" u0="16" u1="0" />
   </ID>
  </S>
  <B t="5.335734" u="ms" />
 </TE>
 <TE>
  <S>
   <P>
    <TC t="0" n="3" st0="2" sz0="1471" st1="5884" sz1="1471" st2="17310728" sz2="2" />
    <TA t="0" n="3" st0="2" sz0="1471" st1="5884" sz1="1471" st2="17310728" sz2="2" />
    <TB t="0" n="3" st0="2" sz0="1471" st1="5884" sz1="1471" st2="17310728" sz2="2" />
    <O t="0" a="0" b="0" o="1" nF="2" nB="1" nS="1" >
     <IA n="3" i0="3" i1="0" i2="2" />
     <IB n="3" i0="1" i1="3" i2="2" />
    </O>
    <DP n="1" d0="Hawaii" CU0="44" MHz0="720" FPC0="128" />
   </P>
   <ID kG0="1" kG1="1" kG2="1" b0="2" b1="2" ppdO="0" ppdLS="0" ppdAll="0" >
    <K i="0" wG0="16" wG1="16" mT0="4" mT1="4" b0="2" b1="2" nlpaA="1" lspaA="4" tspaA="4" nlpeA="1" lspeA="64" tspeA="64" nlpaB="1" lspaB="64" tspaB="64" nlpeB="1" lspeB="4" tspeB="4" u0="4" u1="1" />
   </ID>
  </S>
  <B t="6.391245" u="ms" />
 </TE>
 <TE>
  <S>
   <P>
    <TC t="0" n="3" st0="2" sz0="16" st1="64" sz1="16" st2="2048" sz2="2" />
    <TA t="0" n="3" st0="2" sz0="16" st1="64" sz1="16" st2="2048" sz2="2" />
    <TB t="0" n="3" st0="2" sz0="16" st1="64" sz1="16" st2="2048" sz2="2" />
    <O t="0" a="0" b="0" o="1" nF="2" nB="1" nS="1" >
     <IA n="3" i0="3" i1="0" i2="2" />
     <IB n="3" i0="1" i1="3" i2="2" />
    </O>
    <DP n="1" d0="Hawaii" CU0="44" MHz0="720" FPC0="128" />
   </P>
   <ID kG0="1" kG1="1" kG2="1" b0="2" b1="2" ppdO="0" ppdLS="0" ppdAll="0" >
    <K i="0" wG0="16" wG1="16" mT0="2" mT1="2" b0="2" b1="2" nlpaA="1" lspaA="4" tspaA="4" nlpeA="1" lspeA="32" tspeA="32" nlpaB="1" lspaB="32" tspaB="32" nlpeB="1" lspeB="4" tspeB="4" u0="4" u1="0" />
   </ID>
  </S>
  <B t="0.113422" u="ms" />
 </TE>
 <TE>
  <S>
   <P>
    <TC t="0" n="3" st0="2" sz0="256" st1="1024" sz1="256" st2="524288" sz2="2" />
    <TA t="0" n="3" st0="2" sz0="255" st1="1020" sz1="256" st2="522240" sz2="2" />
    <TB t="0" n="3" st0="2" sz0="256" st1="1024" sz1="255" st2="522240" sz2="2" />
    <O t="0" a="0" b="0" o="1" nF="2" nB="1" nS="1" >
     <IA n="3" i0="3" i1="0" i2="2" />
     <IB n="3" i0="1" i1="3" i2="2" />
    </O>
    <DP n="1" d0="Hawaii" CU0="44" MHz0="720" FPC0="128" />
   </P>
   <ID kG0="2" kG1="2" kG2="1" b0="1" b1="1" ppdO="0" ppdLS="0" ppdAll="0" >
    <K i="0" wG0="8" wG1="8" mT0="2" mT1="2" b0="0" b1="0" nlpaA="1" lspaA="8" tspaA="8" nlpeA="2" lspeA="8" tspeA="16" nlpaB="2" lspaB="8" tspaB="16" nlpeB="1" lspeB="8" tspeB="8" u0="8" u1="1" />
    <K i="1" wG0="8" wG1="8" mT0="2" mT1="2" b0="1" b1="0" nlpaA="1" lspaA="8" tspaA="8" nlpeA="2" lspeA="8" tspeA="16" nlpaB="2" lspaB="8" tspaB="16" nlpeB="1" lspeB="8" tspeB="8" u0="8" u1="1" />
    <K i="2" wG0="8" wG1="8" mT0="2" mT1="2" b0="0" b1="1" nlpaA="1" lspaA="8" tspaA="8" nlpeA="2" lspeA="8" tspeA="16" nlpaB="2" lspaB="8" tspaB="16" nlpeB="1" lspeB="8" tspeB="8" u0="8" u1="1" />
    <K i="3" wG0="8" wG1="8" mT0="2" mT1="2" b0="1" b1="1" nlpaA="1" lspaA="8" tspaA="8" nlpeA="2" lspeA="8" tspeA="16" nlpaB="2" lspaB="8" tspaB="16" nlpeB="1" lspeB="8" tspeB="8" u0="8" u1="1" />
   </ID>
  </S>
  <B t="0.229289" u="ms" />
 </TE>
 <TE>
  <S>
   <P>
    <TC t="0" n="3" st0="2" sz0="2464" st1="9856" sz1="2464" st2="48570368" sz2="2" />
    <TA t="0" n="3" st0="2" sz0="2464" st1="9856" sz1="2464" st2="48570368" sz2="2" />
    <TB t="0" n="3" st0="2" sz0="2464" st1="9856" sz1="2464" st2="48570368" sz2="2" />
    <O t="0" a="0" b="0" o="1" nF="2" nB="1" nS="1" >
     <IA n="3" i0="3" i1="0" i2="2" />
     <IB n="3" i0="1" i1="3" i2="2" />
    </O>
    <DP n="1" d0="Hawaii" CU0="44" MHz0="720" FPC0="128" />
   </P>
   <ID kG0="1" kG1="1" kG2="1" b0="2" b1="2" ppdO="0" ppdLS="0" ppdAll="0" >
    <K i="0" wG0="16" wG1="16" mT0="5" mT1="5" b0="2" b1="2" nlpaA="1" lspaA="16" tspaA="16" nlpeA="5" lspeA="16" tspeA="80" nlpaB="5" lspaB="16" tspaB="80" nlpeB="1" lspeB="16" tspeB="16" u0="16" u1="0" />
   </ID>
  </S>
  <B t="21.757025" u="ms" />
 </TE>
 <TE>
  <S>
   <P>
    <TC t="0" n="3" st0="2" sz0="2192" st1="8768" sz1="2192" st2="38438912" sz2="2" />
    <TA t="0" n="3" st0="2" sz0="2192" st1="8768" sz1="2192" st2="38438912" sz2="2" />
    <TB t="0" n="3" st0="2" sz0="2192" st1="8768" sz1="2192" st2="38438912" sz2="2" />
    <O t="0" a="0" b="0" o="1" nF="2" nB="1" nS="1" >
     <IA n="3" i0="3" i1="0" i2="2" />
     <IB n="3" i0="1" i1="3" i2="2" />
    </O>
    <DP n="1" d0="Hawaii" CU0="44" MHz0="720" FPC0="128" />
   </P>
   <ID kG0="2" kG1="2" kG2="1" b0="1" b1="1" ppdO="0" ppdLS="0" ppdAll="0" >
    <K i="0" wG0="16" wG1="16" mT0="4" mT1="4" b0="0" b1="0" nlpaA="1" lspaA="16" tspaA="16" nlpeA="4" lspeA="16" tspeA="64" nlpaB="4" lspaB="16" tspaB="64" nlpeB="1" lspeB="16" tspeB="16" u0="16" u1="0" />
    <K i="1" wG0="16" wG1="16" mT0="4" mT1="4" b0="1" b1="0" nlpaA="1" lspaA="16" tspaA="16" nlpeA="4" lspeA="16" tspeA="64" nlpaB="4" lspaB="16" tspaB="64" nlpeB="1" lspeB="16" tspeB="16" u0="16" u1="0" />
    <K i="2" wG0="16" wG1="16" mT0="4" mT1="4" b0="0" b1="1" nlpaA="1" lspaA="16" tspaA="16" nlpeA="4" lspeA="16" tspeA="64" nlpaB="4" lspaB="16" tspaB="64" nlpeB="1" lspeB="16" tspeB="16" u0="16" u1="0" />
    <K i="3" wG0="16" wG1="16" mT0="4" mT1="4" b0="1" b1="1" nlpaA="1" lspaA="16" tspaA="16" nlpeA="4" lspeA="16" tspeA="64" nlpaB="4" lspaB="16" tspaB="64" nlpeB="1" lspeB="16" tspeB="16" u0="16" u1="0" />
   </ID>
  </S>
  <B t="15.062180" u="ms" />
 </TE>
 <TE>
  <S>
   <P>
    <TC t="0" n="3" st0="2" sz0="352" st1="1408" sz1="352" st2="991232" sz2="2" />
    <TA t="0" n="3" st0="2" sz0="351" st1="1404" sz1="352" st2="988416" sz2="2" />
    <TB t="0" n="3" st0="2" sz0="352" st1="1408" sz1="351" st2="988416" sz2="2" />
    <O t="0" a="0" b="0" o="1" nF="2" nB="1" nS="1" >
     <IA n="3" i0="3" i1="0" i2="2" />
     <IB n="3" i0="1" i1="3" i2="2" />
    </O>
    <DP n="1" d0="Hawaii" CU0="44" MHz0="720" FPC0="128" />
   </P>
   <ID kG0="1" kG1="1" kG2="1" b0="2" b1="2" ppdO="0" ppdLS="0" ppdAll="0" >
    <K i="0" wG0="16" wG1="16" mT0="4" mT1="4" b0="2" b1="2" nlpaA="1" lspaA="8" tspaA="8" nlpeA="2" lspeA="32" tspeA="64" nlpaB="2" lspaB="32" tspaB="64" nlpeB="1" lspeB="8" tspeB="8" u0="8" u1="1" />
   </ID>
  </S>
  <B t="0.286978" u="ms" />
 </TE>
 <TE>
  <S>
   <P>
    <TC t="0" n="3" st0="2" sz0="15" st1="60" sz1="15" st2="1800" sz2="2" />
    <TA t="0" n="3" st0="2" sz0="15" st1="60" sz1="15" st2="1800" sz2="2" />
    <TB t="0" n="3" st0="2" sz0="15" st1="60" sz1="15" st2="1800" sz2="2" />
    <O t="0" a="0" b="0" o="1" nF="2" nB="1" nS="1" >
     <IA n="3" i0="3" i1="0" i2="2" />
     <IB n="3" i0="1" i1="3" i2="2" />
    </O>
    <DP n="1" d0="Hawaii" CU0="44" MHz0="720" FPC0="128" />
   </P>
   <ID kG0="1" kG1="1" kG2="1" b0="2" b1="2" ppdO="0" ppdLS="0" ppdAll="0" >
    <K i="0" wG0="8" wG1="8" mT0="2" mT1="2" b0="2" b1="2" nlpaA="1" lspaA="4" tspaA="4" nlpeA="1" lspeA="16" tspeA="16" nlpaB="1" lspaB="16" tspaB="16" nlpeB="1" lspeB="4" tspeB="4" u0="4" u1="1" />
   </ID>
  </S>
  <B t="0.118800" u="ms" />
 </TE>
 <TE>
  <S>
   <P>
    <TC t="0" n="3" st0="2" sz0="2191" st1="8764" sz1="2191" st2="38403848" sz2="2" />
    <TA t="0" n="3" st0="2" sz0="2191" st1="8764" sz1="2191" st2="38403848" sz2="2" />
    <TB t="0" n="3" st0="2" sz0="2191" st1="8764" sz1="2191" st2="38403848" sz2="2" />
    <O t="0" a="0" b="0" o="1" nF="2" nB="1" nS="1" >
     <IA n="3" i0="3" i1="0" i2="2" />
     <IB n="3" i0="1" i1="3" i2="2" />
    </O>
    <DP n="1" d0="Hawaii" CU0="44" MHz0="720" FPC0="128" />
   </P>
   <ID kG0="2" kG1="2" kG2="1" b0="1" b1="1" ppdO="0" ppdLS="0" ppdAll="0" >
    <K i="0" wG0="16" wG1="16" mT0="5" mT1="5" b0="0" b1="0" nlpaA="1" lspaA="16" tspaA="16" nlpeA="5" lspeA="16" tspeA="80" nlpaB="5" lspaB="16" tspaB="80" nlpeB="1" lspeB="16" tspeB="16" u0="16" u1="1" />
    <K i="1" wG0="16" wG1="16" mT0="5" mT1="5" b0="1" b1="0" nlpaA="1" lspaA="16" tspaA="16" nlpeA="5" lspeA="16" tspeA="80" nlpaB="5" lspaB="16" tspaB="80" nlpeB="1" lspeB="16" tspeB="16" u0="16" u1="1" />
    <K i="2" wG0="16" wG1="16" mT0="5" mT1="5" b0="0" b1="1" nlpaA="1" lspaA="16" tspaA="16" nlpeA="5" lspeA="16" tspeA="80" nlpaB="5" lspaB="16" tspaB="80" nlpeB="1" lspeB="16" tspeB="16" u0="16" u1="1" />
    <K i="3" wG0="16" wG1="16" mT0="5" mT1="5" b0="1" b1="1" nlpaA="1" lspaA="16" tspaA="16" nlpeA="5" lspeA="16" tspeA="80" nlpaB="5" lspaB="16" tspaB="80" nlpeB="1" lspeB="16" tspeB="16" u0="16" u1="1" />
   </ID>
  </S>
  <B t="18.607113" u="ms" />
 </TE>
 <TE>
  <S>
   <P>
    <TC t="0" n="3" st0="2" sz0="592" st1="2368" sz1="592" st2="2803712" sz2="2" />
    <TA t="0" n="3" st0="2" sz0="592" st1="2368" sz1="592" st2="2803712" sz2="2" />
    <TB t="0" n="3" st0="2" sz0="592" st1="2368" sz1="592" st2="2803712" sz2="2" />
    <O t="0" a="0" b="0" o="1" nF="2" nB="1" nS="1" >
     <IA n="3" i0="3" i1="0" i2="2" />
     <IB n="3" i0="1" i1="3" i2="2" />
    </O>
    <DP n="1" d0="Hawaii" CU0="44" MHz0="720" FPC0="128" />
   </P>
   <ID kG0="1" kG1="1" kG2="1" b0="2" b1="2" ppdO="0" ppdLS="0" ppdAll="0" >
    <K i="0" wG0="16" wG1="16" mT0="5" mT1="5" b0="2" b1="2" nlpaA="1" lspaA="16" tspaA="16" nlpeA="5" lspeA="16" tspeA="80" nlpaB="5" lspaB="16" tspaB="80" nlpeB="1" lspeB="16" tspeB="16" u0="16" u1="0" />
   </ID>
  </S>
  <B t="0.553422" u="ms" />
 </TE>
 <TE>
  <S>
   <P>
    <TC t="0" n="3" st0="2" sz0="896" st1="3584" sz1="896" st2="6422528" sz2="2" />
    <TA t="0" n="3" st0="2" sz0="896" st1="3584" sz1="896" st2="6422528" sz2="2" />
    <TB t="0" n="3" st0="2" sz0="896" st1="3584" sz1="896" st2="6422528" sz2="2" />
    <O t="0" a="0" b="0" o="1" nF="2" nB="1" nS="1" >
     <IA n="3" i0="3" i1="0" i2="2" />
     <IB n="3" i0="1" i1="3" i2="2" />
    </O>
    <DP n="1" d0="Hawaii" CU0="44" MHz0="720" FPC0="128" />
   </P>
   <ID kG0="1" kG1="1" kG2="1" b0="2" b1="2" ppdO="0" ppdLS="0" ppdAll="0" >
    <K i="0" wG0="16" wG1="16" mT0="5" mT1="5" b0="2" b1="2" nlpaA="1" lspaA="16" tspaA="16" nlpeA="5" lspeA="16" tspeA="80" nlpaB="5" lspaB="16" tspaB="80" nlpeB="1" lspeB="16" tspeB="16" u0="16" u1="0" />
   </ID>
  </S>
  <B t="1.893956" u="ms" />
 </TE>
 <TE>
  <S>
   <P>
    <TC t="0" n="3" st0="2" sz0="464" st1="1856" sz1="464" st2="1722368" sz2="2" />
    <TA t="0" n="3" st0="2" sz0="463" st1="1852" sz1="464" st2="1718656" sz2="2" />
    <TB t="0" n="3" st0="2" sz0="464" st1="1856" sz1="463" st2="1718656" sz2="2" />
    <O t="0" a="0" b="0" o="1" nF="2" nB="1" nS="1" >
     <IA n="3" i0="3" i1="0" i2="2" />
     <IB n="3" i0="1" i1="3" i2="2" />
    </O>
    <DP n="1" d0="Hawaii" CU0="44" MHz0="720" FPC0="128" />
   </P>
   <ID kG0="1" kG1="1" kG2="1" b0="2" b1="2" ppdO="0" ppdLS="0" ppdAll="0" >
    <K i="0" wG0="16" wG1="16" mT0="5" mT1="5" b0="2" b1="2" nlpaA="1" lspaA="16" tspaA="16" nlpeA="5" lspeA="16" tspeA="80" nlpaB="5" lspaB="16" tspaB="80" nlpeB="1" lspeB="16" tspeB="16" u0="16" u1="1" />
   </ID>
  </S>
  <B t="0.510400" u="ms" />
 </TE>
 <TE>
  <S>
   <P>
    <TC t="0" n="3" st0="2" sz0="2752" st1="11008" sz1="2752" st2="60588032" sz2="2" />
    <TA t="0" n="3" st0="2" sz0="2751" st1="11004" sz1="2752" st2="60566016" sz2="2" />
    <TB t="0" n="3" st0="2" sz0="2752" st1="11008" sz1="2751" st2="60566016" sz2="2" />
    <O t="0" a="0" b="0" o="1" nF="2" nB="1" nS="1" >
     <IA n="3" i0="3" i1="0" i2="2" />
     <IB n="3" i0="1" i1="3" i2="2" />
    </O>
    <DP n="1" d0="Hawaii" CU0="44" MHz0="720" FPC0="128" />
   </P>
   <ID kG0="2" kG1="2" kG2="1" b0="1" b1="1" ppdO="0" ppdLS="0" ppdAll="0" >
    <K i="0" wG0="16" wG1="16" mT0="4" mT1="4" b0="0" b1="0" nlpaA="1" lspaA="16" tspaA="16" nlpeA="4" lspeA="16" tspeA="64" nlpaB="4" lspaB="16" tspaB="64" nlpeB="1" lspeB="16" tspeB="16" u0="16" u1="1" />
    <K i="1" wG0="16" wG1="16" mT0="4" mT1="4" b0="1" b1="0" nlpaA="1" lspaA="16" tspaA="16" nlpeA="4" lspeA="16" tspeA="64" nlpaB="4" lspaB="16" tspaB="64" nlpeB="1" lspeB="16" tspeB="16" u0="16" u1="1" />
    <K i="2" wG0="16" wG1="16" mT0="4" mT1="4" b0="0" b1="1" nlpaA="1" lspaA="16" tspaA="16" nlpeA="4" lspeA="16" tspeA="64" nlpaB="4" lspaB="16" tspaB="64" nlpeB="1" lspeB="16" tspeB="16" u0="16" u1="1" />
    <K i="3" wG0="16" wG1="16" mT0="4" mT1="4" b0="1" b1="1" nlpaA="1" lspaA="16" tspaA="16" nlpeA="4" lspeA="16" tspeA="64" nlpaB="4" lspaB="16" tspaB="64" nlpeB="1" lspeB="16" tspeB="16" u0="16" u1="1" />
   </ID>
  </S>
  <B t="28.860581" u="ms" />
 </TE>
 <TE>
  <S>
   <P>
    <TC t="0" n="3" st0="2" sz0="1264" st1="5056" sz1="1264" st2="12781568" sz2="2" />
    <TA t="0" n="3" st0="2" sz0="1263" st1="5052" sz1="1264" st2="12771456" sz2="2" />
    <TB t="0" n="3" st0="2" sz0="1264" st1="5056" sz1="1263" st2="12771456" sz2="2" />
    <O t="0" a="0" b="0" o="1" nF="2" nB="1" nS="1" >
     <IA n="3" i0="3" i1="0" i2="2" />
     <IB n="3" i0="1" i1="3" i2="2" />
    </O>
    <DP n="1" d0="Hawaii" CU0="44" MHz0="720" FPC0="128" />
   </P>
   <ID kG0="1" kG1="1" kG2="1" b0="2" b1="2" ppdO="0" ppdLS="0" ppdAll="0" >
    <K i="0" wG0="16" wG1="16" mT0="5" mT1="5" b0="2" b1="2" nlpaA="1" lspaA="16" tspaA="16" nlpeA="5" lspeA="16" tspeA="80" nlpaB="5" lspaB="16" tspaB="80" nlpeB="1" lspeB="16" tspeB="16" u0="16" u1="1" />
   </ID>
  </S>
  <B t="4.003512" u="ms" />
 </TE>
 <TE>
  <S>
   <P>
    <TC t="0" n="3" st0="2" sz0="1264" st1="5056" sz1="1264" st2="12781568" sz2="2" />
    <TA t="0" n="3" st0="2" sz0="1264" st1="5056" sz1="1264" st2="12781568" sz2="2" />
    <TB t="0" n="3" st0="2" sz0="1264" st1="5056" sz1="1264" st2="12781568" sz2="2" />
    <O t="0" a="0" b="0" o="1" nF="2" nB="1" nS="1" >
     <IA n="3" i0="3" i1="0" i2="2" />
     <IB n="3" i0="1" i1="3" i2="2" />
    </O>
    <DP n="1" d0="Hawaii" CU0="44" MHz0="720" FPC0="128" />
   </P>
   <ID kG0="1" kG1="1" kG2="1" b0="2" b1="2" ppdO="0" ppdLS="0" ppdAll="0" >
    <K i="0" wG0="16" wG1="16" mT0="6" mT1="6" b0="2" b1="2" nlpaA="1" lspaA="16" tspaA="16" nlpeA="6" lspeA="16" tspeA="96" nlpaB="6" lspaB="16" tspaB="96" nlpeB="1" lspeB="16" tspeB="16" u0="16" u1="0" />
   </ID>
  </S>
  <B t="3.750756" u="ms" />
 </TE>
 <TE>
  <S>
   <P>
    <TC t="0" n="3" st0="2" sz0="463" st1="1852" sz1="463" st2="1714952" sz2="2" />
    <TA t="0" n="3" st0="2" sz0="464" st1="1856" sz1="463" st2="1718656" sz2="2" />
    <TB t="0" n="3" st0="2" sz0="463" st1="1852" sz1="464" st2="1718656" sz2="2" />
    <O t="0" a="0" b="0" o="1" nF="2" nB="1" nS="1" >
     <IA n="3" i0="3" i1="0" i2="2" />
     <IB n="3" i0="1" i1="3" i2="2" />
    </O>
    <DP n="1" d0="Hawaii" CU0="44" MHz0="720" FPC0="128" />
   </P>
   <ID kG0="1" kG1="1" kG2="1" b0="2" b1="2" ppdO="0" ppdLS="0" ppdAll="0" >
    <K i="0" wG0="16" wG1="16" mT0="4" mT1="4" b0="2" b1="2" nlpaA="1" lspaA="8" tspaA="8" nlpeA="2" lspeA="32" tspeA="64" nlpaB="2" lspaB="32" tspaB="64" nlpeB="1" lspeB="8" tspeB="8" u0="8" u1="0" />
   </ID>
  </S>
  <B t="0.378889" u="ms" />
 </TE>
 <TE>
  <S>
   <P>
    <TC t="0" n="3" st0="2" sz0="1263" st1="5052" sz1="1263" st2="12761352" sz2="2" />
    <TA t="0" n="3" st0="2" sz0="1263" st1="5052" sz1="1263" st2="12761352" sz2="2" />
    <TB t="0" n="3" st0="2" sz0="1263" st1="5052" sz1="1263" st2="12761352" sz2="2" />
    <O t="0" a="0" b="0" o="1" nF="2" nB="1" nS="1" >
     <IA n="3" i0="3" i1="0" i2="2" />
     <IB n="3" i0="1" i1="3" i2="2" />
    </O>
    <DP n="1" d0="Hawaii" CU0="44" MHz0="720" FPC0="128" />
   </P>
   <ID kG0="1" kG1="1" kG2="1" b0="2" b1="2" ppdO="0" ppdLS="0" ppdAll="0" >
    <K i="0" wG0="16" wG1="16" mT0="5" mT1="5" b0="2" b1="2" nlpaA="1" lspaA="16" tspaA="16" nlpeA="5" lspeA="16" tspeA="80" nlpaB="5" lspaB="16" tspaB="80" nlpeB="1" lspeB="16" tspeB="16" u0="16" u1="1" />
   </ID>
  </S>
  <B t="4.271423" u="ms" />
 </TE>
</CobaltLog>
